[{"CastIndex": 1, "Type": 1, "Size": 2, "LanePosition": 3, "JudgeTime": 1.7518248558044434}, {"CastIndex": 1, "Type": 1, "Size": 2, "LanePosition": 0, "JudgeTime": 1.7518248558044434}, {"CastIndex": 1, "Type": 4, "Size": 3, "LanePosition": 0, "JudgeTime": 1.8613139390945435}, {"CastIndex": 1, "Type": 4, "Size": 3, "LanePosition": 0, "JudgeTime": 1.9708030223846436}, {"CastIndex": 1, "Type": 4, "Size": 3, "LanePosition": 0, "JudgeTime": 2.080291986465454}, {"CastIndex": 1, "Type": 1, "Size": 2, "LanePosition": 3, "JudgeTime": 2.080291986465454}, {"CastIndex": 1, "Type": 4, "Size": 3, "LanePosition": 0, "JudgeTime": 2.1897811889648438}, {"CastIndex": 1, "Type": 4, "Size": 3, "LanePosition": 0, "JudgeTime": 2.2992701530456543}, {"CastIndex": 1, "Type": 1, "Size": 2, "LanePosition": 3, "JudgeTime": 2.408759117126465}, {"CastIndex": 1, "Type": 4, "Size": 3, "LanePosition": 0, "JudgeTime": 2.408759117126465}, {"CastIndex": 1, "Type": 4, "Size": 3, "LanePosition": 0, "JudgeTime": 2.5182483196258545}, {"CastIndex": 1, "Type": 1, "Size": 2, "LanePosition": 3, "JudgeTime": 2.627737283706665}, {"CastIndex": 1, "Type": 4, "Size": 3, "LanePosition": 0, "JudgeTime": 2.627737283706665}, {"CastIndex": 1, "Type": 4, "Size": 3, "LanePosition": 0, "JudgeTime": 2.7372262477874756}, {"CastIndex": 1, "Type": 4, "Size": 3, "LanePosition": 0, "JudgeTime": 2.8467154502868652}, {"CastIndex": 1, "Type": 1, "Size": 2, "LanePosition": 3, "JudgeTime": 2.956204414367676}, {"CastIndex": 1, "Type": 4, "Size": 3, "LanePosition": 0, "JudgeTime": 2.956204414367676}, {"CastIndex": 1, "Type": 4, "Size": 3, "LanePosition": 0, "JudgeTime": 3.0656933784484863}, {"CastIndex": 1, "Type": 4, "Size": 3, "LanePosition": 0, "JudgeTime": 3.175182580947876}, {"CastIndex": 1, "Type": 1, "Size": 2, "LanePosition": 3, "JudgeTime": 3.2846715450286865}, {"CastIndex": 1, "Type": 4, "Size": 3, "LanePosition": 0, "JudgeTime": 3.2846715450286865}, {"CastIndex": 1, "Type": 4, "Size": 3, "LanePosition": 0, "JudgeTime": 3.394160747528076}, {"CastIndex": 1, "Type": 3, "Size": 3, "LanePosition": 0, "JudgeTime": 3.5036497116088867}, {"CastIndex": 1, "Type": 1, "Size": 2, "LanePosition": 3, "JudgeTime": 3.5036497116088867}, {"CastIndex": 1, "Type": 4, "Size": 3, "LanePosition": 0, "JudgeTime": 3.6131386756896973}, {"CastIndex": 1, "Type": 4, "Size": 3, "LanePosition": 0, "JudgeTime": 3.722627878189087}, {"CastIndex": 1, "Type": 1, "Size": 2, "LanePosition": 3, "JudgeTime": 3.8321168422698975}, {"CastIndex": 1, "Type": 4, "Size": 3, "LanePosition": 0, "JudgeTime": 3.8321168422698975}, {"CastIndex": 1, "Type": 4, "Size": 3, "LanePosition": 0, "JudgeTime": 3.941606044769287}, {"CastIndex": 1, "Type": 4, "Size": 3, "LanePosition": 0, "JudgeTime": 4.051095008850098}, {"CastIndex": 1, "Type": 1, "Size": 2, "LanePosition": 3, "JudgeTime": 4.160583972930908}, {"CastIndex": 1, "Type": 4, "Size": 3, "LanePosition": 0, "JudgeTime": 4.160583972930908}, {"CastIndex": 1, "Type": 4, "Size": 3, "LanePosition": 0, "JudgeTime": 4.270072937011719}, {"CastIndex": 1, "Type": 1, "Size": 2, "LanePosition": 3, "JudgeTime": 4.3795623779296875}, {"CastIndex": 1, "Type": 4, "Size": 3, "LanePosition": 0, "JudgeTime": 4.3795623779296875}, {"CastIndex": 1, "Type": 4, "Size": 3, "LanePosition": 0, "JudgeTime": 4.489051342010498}, {"CastIndex": 1, "Type": 4, "Size": 3, "LanePosition": 0, "JudgeTime": 4.598540306091309}, {"CastIndex": 1, "Type": 4, "Size": 3, "LanePosition": 0, "JudgeTime": 4.708029270172119}, {"CastIndex": 1, "Type": 4, "Size": 3, "LanePosition": 0, "JudgeTime": 4.81751823425293}, {"CastIndex": 1, "Type": 4, "Size": 3, "LanePosition": 0, "JudgeTime": 4.92700719833374}, {"CastIndex": 1, "Type": 4, "Size": 3, "LanePosition": 0, "JudgeTime": 5.036496639251709}, {"CastIndex": 1, "Type": 4, "Size": 3, "LanePosition": 0, "JudgeTime": 5.1459856033325195}, {"CastIndex": 2, "Type": 2, "Size": 2, "LanePosition": 0, "JudgeTime": 5.25547456741333}, {"CastIndex": 2, "Type": 1, "Size": 2, "LanePosition": 3, "JudgeTime": 5.25547456741333}, {"CastIndex": 2, "Type": 4, "Size": 3, "LanePosition": 2, "JudgeTime": 5.364963531494141}, {"CastIndex": 2, "Type": 4, "Size": 3, "LanePosition": 2, "JudgeTime": 5.474452495574951}, {"CastIndex": 2, "Type": 1, "Size": 2, "LanePosition": 0, "JudgeTime": 5.58394193649292}, {"CastIndex": 2, "Type": 4, "Size": 3, "LanePosition": 2, "JudgeTime": 5.58394193649292}, {"CastIndex": 2, "Type": 4, "Size": 3, "LanePosition": 2, "JudgeTime": 5.6934309005737305}, {"CastIndex": 2, "Type": 4, "Size": 3, "LanePosition": 2, "JudgeTime": 5.802919864654541}, {"CastIndex": 2, "Type": 1, "Size": 2, "LanePosition": 0, "JudgeTime": 5.912408828735352}, {"CastIndex": 2, "Type": 4, "Size": 3, "LanePosition": 2, "JudgeTime": 5.912408828735352}, {"CastIndex": 2, "Type": 4, "Size": 3, "LanePosition": 2, "JudgeTime": 6.021897792816162}, {"CastIndex": 2, "Type": 4, "Size": 3, "LanePosition": 2, "JudgeTime": 6.131386756896973}, {"CastIndex": 2, "Type": 1, "Size": 2, "LanePosition": 0, "JudgeTime": 6.131386756896973}, {"CastIndex": 2, "Type": 4, "Size": 3, "LanePosition": 2, "JudgeTime": 6.240876197814941}, {"CastIndex": 2, "Type": 4, "Size": 3, "LanePosition": 2, "JudgeTime": 6.350365161895752}, {"CastIndex": 2, "Type": 4, "Size": 3, "LanePosition": 2, "JudgeTime": 6.4598541259765625}, {"CastIndex": 2, "Type": 1, "Size": 2, "LanePosition": 0, "JudgeTime": 6.4598541259765625}, {"CastIndex": 2, "Type": 4, "Size": 3, "LanePosition": 2, "JudgeTime": 6.569343090057373}, {"CastIndex": 2, "Type": 4, "Size": 3, "LanePosition": 2, "JudgeTime": 6.678832054138184}, {"CastIndex": 2, "Type": 1, "Size": 2, "LanePosition": 0, "JudgeTime": 6.788321495056152}, {"CastIndex": 2, "Type": 4, "Size": 3, "LanePosition": 2, "JudgeTime": 6.788321495056152}, {"CastIndex": 2, "Type": 4, "Size": 3, "LanePosition": 2, "JudgeTime": 6.897810459136963}, {"CastIndex": 2, "Type": 1, "Size": 2, "LanePosition": 0, "JudgeTime": 7.007299423217773}, {"CastIndex": 2, "Type": 3, "Size": 3, "LanePosition": 2, "JudgeTime": 7.007299423217773}, {"CastIndex": 2, "Type": 4, "Size": 3, "LanePosition": 2, "JudgeTime": 7.116788387298584}, {"CastIndex": 2, "Type": 4, "Size": 3, "LanePosition": 2, "JudgeTime": 7.2262773513793945}, {"CastIndex": 2, "Type": 4, "Size": 3, "LanePosition": 2, "JudgeTime": 7.335766792297363}, {"CastIndex": 2, "Type": 1, "Size": 2, "LanePosition": 0, "JudgeTime": 7.335766792297363}, {"CastIndex": 2, "Type": 4, "Size": 3, "LanePosition": 2, "JudgeTime": 7.445255756378174}, {"CastIndex": 2, "Type": 4, "Size": 3, "LanePosition": 2, "JudgeTime": 7.554744720458984}, {"CastIndex": 2, "Type": 1, "Size": 2, "LanePosition": 0, "JudgeTime": 7.664233684539795}, {"CastIndex": 2, "Type": 4, "Size": 3, "LanePosition": 2, "JudgeTime": 7.664233684539795}, {"CastIndex": 2, "Type": 4, "Size": 3, "LanePosition": 2, "JudgeTime": 7.7737226486206055}, {"CastIndex": 2, "Type": 4, "Size": 3, "LanePosition": 2, "JudgeTime": 7.883212089538574}, {"CastIndex": 2, "Type": 4, "Size": 3, "LanePosition": 2, "JudgeTime": 7.992701053619385}, {"CastIndex": 2, "Type": 4, "Size": 3, "LanePosition": 2, "JudgeTime": 8.102190017700195}, {"CastIndex": 2, "Type": 4, "Size": 3, "LanePosition": 2, "JudgeTime": 8.211679458618164}, {"CastIndex": 2, "Type": 4, "Size": 3, "LanePosition": 2, "JudgeTime": 8.321167945861816}, {"CastIndex": 2, "Type": 4, "Size": 3, "LanePosition": 2, "JudgeTime": 8.430657386779785}, {"CastIndex": 2, "Type": 4, "Size": 3, "LanePosition": 2, "JudgeTime": 8.540145874023438}, {"CastIndex": 2, "Type": 4, "Size": 3, "LanePosition": 2, "JudgeTime": 8.649635314941406}, {"CastIndex": 3, "Type": 2, "Size": 2, "LanePosition": 3, "JudgeTime": 8.759124755859375}, {"CastIndex": 3, "Type": 1, "Size": 2, "LanePosition": 0, "JudgeTime": 8.759124755859375}, {"CastIndex": 3, "Type": 4, "Size": 3, "LanePosition": 0, "JudgeTime": 8.868614196777344}, {"CastIndex": 3, "Type": 4, "Size": 3, "LanePosition": 0, "JudgeTime": 8.978102684020996}, {"CastIndex": 3, "Type": 4, "Size": 3, "LanePosition": 0, "JudgeTime": 9.087592124938965}, {"CastIndex": 3, "Type": 1, "Size": 2, "LanePosition": 3, "JudgeTime": 9.087592124938965}, {"CastIndex": 3, "Type": 4, "Size": 3, "LanePosition": 0, "JudgeTime": 9.197080612182617}, {"CastIndex": 3, "Type": 4, "Size": 3, "LanePosition": 0, "JudgeTime": 9.306570053100586}, {"CastIndex": 3, "Type": 4, "Size": 3, "LanePosition": 0, "JudgeTime": 9.416059494018555}, {"CastIndex": 3, "Type": 1, "Size": 2, "LanePosition": 3, "JudgeTime": 9.416059494018555}, {"CastIndex": 3, "Type": 4, "Size": 3, "LanePosition": 0, "JudgeTime": 9.525547981262207}, {"CastIndex": 3, "Type": 4, "Size": 3, "LanePosition": 0, "JudgeTime": 9.635037422180176}, {"CastIndex": 3, "Type": 1, "Size": 2, "LanePosition": 3, "JudgeTime": 9.635037422180176}, {"CastIndex": 3, "Type": 4, "Size": 3, "LanePosition": 0, "JudgeTime": 9.744525909423828}, {"CastIndex": 3, "Type": 4, "Size": 3, "LanePosition": 0, "JudgeTime": 9.854015350341797}, {"CastIndex": 3, "Type": 1, "Size": 2, "LanePosition": 3, "JudgeTime": 9.963504791259766}, {"CastIndex": 3, "Type": 4, "Size": 3, "LanePosition": 0, "JudgeTime": 9.963504791259766}, {"CastIndex": 3, "Type": 4, "Size": 3, "LanePosition": 0, "JudgeTime": 10.072993278503418}, {"CastIndex": 3, "Type": 4, "Size": 3, "LanePosition": 0, "JudgeTime": 10.182482719421387}, {"CastIndex": 3, "Type": 1, "Size": 2, "LanePosition": 3, "JudgeTime": 10.291971206665039}, {"CastIndex": 3, "Type": 4, "Size": 3, "LanePosition": 0, "JudgeTime": 10.291971206665039}, {"CastIndex": 3, "Type": 4, "Size": 3, "LanePosition": 0, "JudgeTime": 10.401460647583008}, {"CastIndex": 3, "Type": 4, "Size": 3, "LanePosition": 0, "JudgeTime": 10.510950088500977}, {"CastIndex": 3, "Type": 1, "Size": 2, "LanePosition": 3, "JudgeTime": 10.510950088500977}, {"CastIndex": 3, "Type": 4, "Size": 3, "LanePosition": 0, "JudgeTime": 10.620439529418945}, {"CastIndex": 3, "Type": 4, "Size": 3, "LanePosition": 0, "JudgeTime": 10.729928016662598}, {"CastIndex": 3, "Type": 4, "Size": 3, "LanePosition": 0, "JudgeTime": 10.839417457580566}, {"CastIndex": 3, "Type": 1, "Size": 2, "LanePosition": 3, "JudgeTime": 10.839417457580566}, {"CastIndex": 3, "Type": 4, "Size": 3, "LanePosition": 0, "JudgeTime": 10.948905944824219}, {"CastIndex": 3, "Type": 4, "Size": 3, "LanePosition": 0, "JudgeTime": 11.058395385742188}, {"CastIndex": 3, "Type": 1, "Size": 2, "LanePosition": 3, "JudgeTime": 11.167884826660156}, {"CastIndex": 3, "Type": 4, "Size": 3, "LanePosition": 0, "JudgeTime": 11.167884826660156}, {"CastIndex": 3, "Type": 4, "Size": 3, "LanePosition": 0, "JudgeTime": 11.277373313903809}, {"CastIndex": 3, "Type": 4, "Size": 3, "LanePosition": 0, "JudgeTime": 11.386862754821777}, {"CastIndex": 3, "Type": 1, "Size": 2, "LanePosition": 3, "JudgeTime": 11.386862754821777}, {"CastIndex": 3, "Type": 4, "Size": 3, "LanePosition": 0, "JudgeTime": 11.49635124206543}, {"CastIndex": 3, "Type": 4, "Size": 3, "LanePosition": 0, "JudgeTime": 11.605840682983398}, {"CastIndex": 3, "Type": 4, "Size": 3, "LanePosition": 0, "JudgeTime": 11.715330123901367}, {"CastIndex": 3, "Type": 3, "Size": 3, "LanePosition": 0, "JudgeTime": 11.82481861114502}, {"CastIndex": 3, "Type": 4, "Size": 3, "LanePosition": 0, "JudgeTime": 11.934308052062988}, {"CastIndex": 3, "Type": 4, "Size": 3, "LanePosition": 0, "JudgeTime": 12.04379653930664}, {"CastIndex": 3, "Type": 4, "Size": 3, "LanePosition": 0, "JudgeTime": 12.15328598022461}, {"CastIndex": 4, "Type": 1, "Size": 2, "LanePosition": 3, "JudgeTime": 12.262775421142578}, {"CastIndex": 4, "Type": 2, "Size": 2, "LanePosition": 0, "JudgeTime": 12.262775421142578}, {"CastIndex": 4, "Type": 4, "Size": 3, "LanePosition": 2, "JudgeTime": 12.372264862060547}, {"CastIndex": 4, "Type": 4, "Size": 3, "LanePosition": 2, "JudgeTime": 12.4817533493042}, {"CastIndex": 4, "Type": 4, "Size": 3, "LanePosition": 2, "JudgeTime": 12.591242790222168}, {"CastIndex": 4, "Type": 1, "Size": 2, "LanePosition": 0, "JudgeTime": 12.591242790222168}, {"CastIndex": 4, "Type": 4, "Size": 3, "LanePosition": 2, "JudgeTime": 12.70073127746582}, {"CastIndex": 4, "Type": 4, "Size": 3, "LanePosition": 2, "JudgeTime": 12.810220718383789}, {"CastIndex": 4, "Type": 1, "Size": 2, "LanePosition": 0, "JudgeTime": 12.919710159301758}, {"CastIndex": 4, "Type": 4, "Size": 3, "LanePosition": 2, "JudgeTime": 12.919710159301758}, {"CastIndex": 4, "Type": 4, "Size": 3, "LanePosition": 2, "JudgeTime": 13.02919864654541}, {"CastIndex": 4, "Type": 1, "Size": 2, "LanePosition": 0, "JudgeTime": 13.138688087463379}, {"CastIndex": 4, "Type": 4, "Size": 3, "LanePosition": 2, "JudgeTime": 13.138688087463379}, {"CastIndex": 4, "Type": 4, "Size": 3, "LanePosition": 2, "JudgeTime": 13.248176574707031}, {"CastIndex": 4, "Type": 4, "Size": 3, "LanePosition": 2, "JudgeTime": 13.357666015625}, {"CastIndex": 4, "Type": 1, "Size": 2, "LanePosition": 0, "JudgeTime": 13.467155456542969}, {"CastIndex": 4, "Type": 4, "Size": 3, "LanePosition": 2, "JudgeTime": 13.467155456542969}, {"CastIndex": 4, "Type": 4, "Size": 3, "LanePosition": 2, "JudgeTime": 13.576643943786621}, {"CastIndex": 4, "Type": 4, "Size": 3, "LanePosition": 2, "JudgeTime": 13.68613338470459}, {"CastIndex": 4, "Type": 1, "Size": 2, "LanePosition": 0, "JudgeTime": 13.795621871948242}, {"CastIndex": 4, "Type": 3, "Size": 3, "LanePosition": 2, "JudgeTime": 13.795621871948242}, {"CastIndex": 4, "Type": 4, "Size": 3, "LanePosition": 2, "JudgeTime": 13.905111312866211}, {"CastIndex": 4, "Type": 4, "Size": 3, "LanePosition": 2, "JudgeTime": 14.01460075378418}, {"CastIndex": 4, "Type": 1, "Size": 2, "LanePosition": 0, "JudgeTime": 14.01460075378418}, {"CastIndex": 4, "Type": 4, "Size": 3, "LanePosition": 2, "JudgeTime": 14.124090194702148}, {"CastIndex": 4, "Type": 4, "Size": 3, "LanePosition": 2, "JudgeTime": 14.2335786819458}, {"CastIndex": 4, "Type": 4, "Size": 3, "LanePosition": 2, "JudgeTime": 14.34306812286377}, {"CastIndex": 4, "Type": 1, "Size": 2, "LanePosition": 0, "JudgeTime": 14.34306812286377}, {"CastIndex": 4, "Type": 4, "Size": 3, "LanePosition": 2, "JudgeTime": 14.452556610107422}, {"CastIndex": 4, "Type": 4, "Size": 3, "LanePosition": 2, "JudgeTime": 14.56204605102539}, {"CastIndex": 4, "Type": 1, "Size": 2, "LanePosition": 0, "JudgeTime": 14.67153549194336}, {"CastIndex": 4, "Type": 4, "Size": 3, "LanePosition": 2, "JudgeTime": 14.67153549194336}, {"CastIndex": 4, "Type": 4, "Size": 3, "LanePosition": 2, "JudgeTime": 14.781023979187012}, {"CastIndex": 4, "Type": 4, "Size": 3, "LanePosition": 2, "JudgeTime": 14.89051342010498}, {"CastIndex": 4, "Type": 4, "Size": 3, "LanePosition": 2, "JudgeTime": 15.000001907348633}, {"CastIndex": 4, "Type": 4, "Size": 3, "LanePosition": 2, "JudgeTime": 15.109491348266602}, {"CastIndex": 4, "Type": 4, "Size": 3, "LanePosition": 2, "JudgeTime": 15.21898078918457}, {"CastIndex": 4, "Type": 2, "Size": 2, "LanePosition": 3, "JudgeTime": 15.328469276428223}, {"CastIndex": 0, "Type": 1, "Size": 2, "LanePosition": 3, "JudgeTime": 15.985404014587402}, {"CastIndex": 0, "Type": 1, "Size": 2, "LanePosition": 1, "JudgeTime": 16.204381942749023}, {"CastIndex": 0, "Type": 1, "Size": 2, "LanePosition": 3, "JudgeTime": 16.42336082458496}, {"CastIndex": 0, "Type": 1, "Size": 2, "LanePosition": 1, "JudgeTime": 16.642337799072266}, {"CastIndex": 0, "Type": 4, "Size": 2, "LanePosition": 1, "JudgeTime": 16.751827239990234}, {"CastIndex": 0, "Type": 4, "Size": 2, "LanePosition": 1, "JudgeTime": 16.861316680908203}, {"CastIndex": 0, "Type": 1, "Size": 2, "LanePosition": 3, "JudgeTime": 16.970806121826172}, {"CastIndex": 0, "Type": 2, "Size": 2, "LanePosition": 1, "JudgeTime": 16.970806121826172}, {"CastIndex": 0, "Type": 4, "Size": 2, "LanePosition": 3, "JudgeTime": 17.08029556274414}, {"CastIndex": 0, "Type": 4, "Size": 2, "LanePosition": 3, "JudgeTime": 17.189783096313477}, {"CastIndex": 0, "Type": 4, "Size": 2, "LanePosition": 3, "JudgeTime": 17.299272537231445}, {"CastIndex": 0, "Type": 1, "Size": 2, "LanePosition": 0, "JudgeTime": 17.299272537231445}, {"CastIndex": 0, "Type": 4, "Size": 2, "LanePosition": 0, "JudgeTime": 17.408761978149414}, {"CastIndex": 0, "Type": 4, "Size": 2, "LanePosition": 3, "JudgeTime": 17.408761978149414}, {"CastIndex": 0, "Type": 4, "Size": 2, "LanePosition": 3, "JudgeTime": 17.518251419067383}, {"CastIndex": 0, "Type": 4, "Size": 2, "LanePosition": 0, "JudgeTime": 17.518251419067383}, {"CastIndex": 0, "Type": 4, "Size": 2, "LanePosition": 0, "JudgeTime": 17.62774085998535}, {"CastIndex": 0, "Type": 4, "Size": 2, "LanePosition": 3, "JudgeTime": 17.62774085998535}, {"CastIndex": 0, "Type": 2, "Size": 2, "LanePosition": 3, "JudgeTime": 17.73723030090332}, {"CastIndex": 0, "Type": 4, "Size": 2, "LanePosition": 0, "JudgeTime": 17.73723030090332}, {"CastIndex": 0, "Type": 4, "Size": 2, "LanePosition": 0, "JudgeTime": 17.846717834472656}, {"CastIndex": 0, "Type": 4, "Size": 2, "LanePosition": 0, "JudgeTime": 17.956207275390625}, {"CastIndex": 0, "Type": 4, "Size": 2, "LanePosition": 0, "JudgeTime": 18.065696716308594}, {"CastIndex": 0, "Type": 4, "Size": 2, "LanePosition": 0, "JudgeTime": 18.175186157226562}, {"CastIndex": 0, "Type": 4, "Size": 2, "LanePosition": 0, "JudgeTime": 18.28467559814453}, {"CastIndex": 0, "Type": 4, "Size": 2, "LanePosition": 0, "JudgeTime": 18.394163131713867}, {"CastIndex": 0, "Type": 4, "Size": 2, "LanePosition": 0, "JudgeTime": 18.503652572631836}, {"CastIndex": 0, "Type": 4, "Size": 2, "LanePosition": 0, "JudgeTime": 18.613142013549805}, {"CastIndex": 0, "Type": 4, "Size": 2, "LanePosition": 0, "JudgeTime": 18.722631454467773}, {"CastIndex": 0, "Type": 2, "Size": 2, "LanePosition": 0, "JudgeTime": 18.832120895385742}, {"CastIndex": 0, "Type": 1, "Size": 2, "LanePosition": 2, "JudgeTime": 19.489055633544922}, {"CastIndex": 0, "Type": 1, "Size": 2, "LanePosition": 3, "JudgeTime": 19.708032608032227}, {"CastIndex": 0, "Type": 1, "Size": 2, "LanePosition": 1, "JudgeTime": 19.927011489868164}, {"CastIndex": 0, "Type": 1, "Size": 2, "LanePosition": 3, "JudgeTime": 20.14598846435547}, {"CastIndex": 0, "Type": 4, "Size": 2, "LanePosition": 3, "JudgeTime": 20.255477905273438}, {"CastIndex": 0, "Type": 4, "Size": 2, "LanePosition": 3, "JudgeTime": 20.364967346191406}, {"CastIndex": 0, "Type": 1, "Size": 2, "LanePosition": 0, "JudgeTime": 20.474456787109375}, {"CastIndex": 0, "Type": 2, "Size": 2, "LanePosition": 3, "JudgeTime": 20.474456787109375}, {"CastIndex": 0, "Type": 4, "Size": 2, "LanePosition": 0, "JudgeTime": 20.583946228027344}, {"CastIndex": 0, "Type": 4, "Size": 2, "LanePosition": 0, "JudgeTime": 20.69343376159668}, {"CastIndex": 0, "Type": 4, "Size": 2, "LanePosition": 0, "JudgeTime": 20.80292320251465}, {"CastIndex": 0, "Type": 1, "Size": 2, "LanePosition": 3, "JudgeTime": 20.80292320251465}, {"CastIndex": 0, "Type": 4, "Size": 2, "LanePosition": 3, "JudgeTime": 20.912412643432617}, {"CastIndex": 0, "Type": 4, "Size": 2, "LanePosition": 0, "JudgeTime": 20.912412643432617}, {"CastIndex": 0, "Type": 4, "Size": 2, "LanePosition": 3, "JudgeTime": 21.021902084350586}, {"CastIndex": 0, "Type": 4, "Size": 2, "LanePosition": 0, "JudgeTime": 21.021902084350586}, {"CastIndex": 0, "Type": 4, "Size": 2, "LanePosition": 3, "JudgeTime": 21.131391525268555}, {"CastIndex": 0, "Type": 4, "Size": 2, "LanePosition": 0, "JudgeTime": 21.131391525268555}, {"CastIndex": 0, "Type": 4, "Size": 2, "LanePosition": 3, "JudgeTime": 21.240880966186523}, {"CastIndex": 0, "Type": 2, "Size": 2, "LanePosition": 0, "JudgeTime": 21.240880966186523}, {"CastIndex": 0, "Type": 4, "Size": 2, "LanePosition": 3, "JudgeTime": 21.35036849975586}, {"CastIndex": 0, "Type": 4, "Size": 2, "LanePosition": 3, "JudgeTime": 21.459857940673828}, {"CastIndex": 0, "Type": 4, "Size": 2, "LanePosition": 3, "JudgeTime": 21.569347381591797}, {"CastIndex": 0, "Type": 4, "Size": 2, "LanePosition": 3, "JudgeTime": 21.678836822509766}, {"CastIndex": 0, "Type": 4, "Size": 2, "LanePosition": 3, "JudgeTime": 21.788326263427734}, {"CastIndex": 0, "Type": 4, "Size": 2, "LanePosition": 3, "JudgeTime": 21.89781379699707}, {"CastIndex": 0, "Type": 4, "Size": 2, "LanePosition": 3, "JudgeTime": 22.00730323791504}, {"CastIndex": 0, "Type": 4, "Size": 2, "LanePosition": 3, "JudgeTime": 22.116792678833008}, {"CastIndex": 0, "Type": 4, "Size": 2, "LanePosition": 3, "JudgeTime": 22.226282119750977}, {"CastIndex": 0, "Type": 2, "Size": 2, "LanePosition": 3, "JudgeTime": 22.335771560668945}, {"CastIndex": 0, "Type": 1, "Size": 2, "LanePosition": 1, "JudgeTime": 23.430662155151367}, {"CastIndex": 0, "Type": 1, "Size": 2, "LanePosition": 2, "JudgeTime": 23.649639129638672}, {"CastIndex": 0, "Type": 4, "Size": 2, "LanePosition": 2, "JudgeTime": 23.75912857055664}, {"CastIndex": 0, "Type": 4, "Size": 2, "LanePosition": 2, "JudgeTime": 23.86861801147461}, {"CastIndex": 0, "Type": 2, "Size": 2, "LanePosition": 2, "JudgeTime": 23.978107452392578}, {"CastIndex": 0, "Type": 1, "Size": 2, "LanePosition": 0, "JudgeTime": 23.978107452392578}, {"CastIndex": 0, "Type": 4, "Size": 2, "LanePosition": 0, "JudgeTime": 24.087596893310547}, {"CastIndex": 0, "Type": 4, "Size": 2, "LanePosition": 0, "JudgeTime": 24.197084426879883}, {"CastIndex": 0, "Type": 1, "Size": 2, "LanePosition": 3, "JudgeTime": 24.30657386779785}, {"CastIndex": 0, "Type": 4, "Size": 2, "LanePosition": 0, "JudgeTime": 24.30657386779785}, {"CastIndex": 0, "Type": 4, "Size": 2, "LanePosition": 3, "JudgeTime": 24.41606330871582}, {"CastIndex": 0, "Type": 4, "Size": 2, "LanePosition": 0, "JudgeTime": 24.41606330871582}, {"CastIndex": 0, "Type": 4, "Size": 2, "LanePosition": 3, "JudgeTime": 24.52555274963379}, {"CastIndex": 0, "Type": 4, "Size": 2, "LanePosition": 0, "JudgeTime": 24.52555274963379}, {"CastIndex": 0, "Type": 4, "Size": 2, "LanePosition": 3, "JudgeTime": 24.635042190551758}, {"CastIndex": 0, "Type": 4, "Size": 2, "LanePosition": 0, "JudgeTime": 24.635042190551758}, {"CastIndex": 0, "Type": 4, "Size": 2, "LanePosition": 0, "JudgeTime": 24.744531631469727}, {"CastIndex": 0, "Type": 4, "Size": 2, "LanePosition": 3, "JudgeTime": 24.744531631469727}, {"CastIndex": 0, "Type": 4, "Size": 2, "LanePosition": 3, "JudgeTime": 24.854019165039062}, {"CastIndex": 0, "Type": 4, "Size": 2, "LanePosition": 0, "JudgeTime": 24.854019165039062}, {"CastIndex": 0, "Type": 2, "Size": 2, "LanePosition": 3, "JudgeTime": 24.96350860595703}, {"CastIndex": 0, "Type": 2, "Size": 2, "LanePosition": 0, "JudgeTime": 24.96350860595703}, {"CastIndex": 0, "Type": 1, "Size": 2, "LanePosition": 0, "JudgeTime": 25.18248748779297}, {"CastIndex": 0, "Type": 1, "Size": 2, "LanePosition": 3, "JudgeTime": 25.401464462280273}, {"CastIndex": 0, "Type": 4, "Size": 2, "LanePosition": 3, "JudgeTime": 25.510953903198242}, {"CastIndex": 0, "Type": 4, "Size": 2, "LanePosition": 3, "JudgeTime": 25.62044334411621}, {"CastIndex": 0, "Type": 2, "Size": 2, "LanePosition": 3, "JudgeTime": 25.72993278503418}, {"CastIndex": 0, "Type": 1, "Size": 2, "LanePosition": 0, "JudgeTime": 25.72993278503418}, {"CastIndex": 0, "Type": 4, "Size": 2, "LanePosition": 0, "JudgeTime": 25.83942222595215}, {"CastIndex": 0, "Type": 4, "Size": 2, "LanePosition": 0, "JudgeTime": 25.948909759521484}, {"CastIndex": 0, "Type": 1, "Size": 1, "LanePosition": 2, "JudgeTime": 26.058399200439453}, {"CastIndex": 0, "Type": 2, "Size": 2, "LanePosition": 0, "JudgeTime": 26.058399200439453}, {"CastIndex": 0, "Type": 4, "Size": 1, "LanePosition": 2, "JudgeTime": 26.167888641357422}, {"CastIndex": 0, "Type": 4, "Size": 1, "LanePosition": 2, "JudgeTime": 26.27737808227539}, {"CastIndex": 0, "Type": 4, "Size": 1, "LanePosition": 2, "JudgeTime": 26.38686752319336}, {"CastIndex": 0, "Type": 4, "Size": 1, "LanePosition": 2, "JudgeTime": 26.496356964111328}, {"CastIndex": 0, "Type": 4, "Size": 1, "LanePosition": 2, "JudgeTime": 26.605844497680664}, {"CastIndex": 0, "Type": 4, "Size": 1, "LanePosition": 2, "JudgeTime": 26.715333938598633}, {"CastIndex": 0, "Type": 4, "Size": 1, "LanePosition": 2, "JudgeTime": 26.8248233795166}, {"CastIndex": 0, "Type": 4, "Size": 1, "LanePosition": 2, "JudgeTime": 26.93431282043457}, {"CastIndex": 0, "Type": 4, "Size": 1, "LanePosition": 2, "JudgeTime": 27.04380226135254}, {"CastIndex": 0, "Type": 4, "Size": 1, "LanePosition": 2, "JudgeTime": 27.153289794921875}, {"CastIndex": 0, "Type": 4, "Size": 1, "LanePosition": 2, "JudgeTime": 27.262779235839844}, {"CastIndex": 0, "Type": 4, "Size": 1, "LanePosition": 2, "JudgeTime": 27.372268676757812}, {"CastIndex": 0, "Type": 4, "Size": 1, "LanePosition": 2, "JudgeTime": 27.48175811767578}, {"CastIndex": 0, "Type": 4, "Size": 1, "LanePosition": 2, "JudgeTime": 27.59124755859375}, {"CastIndex": 0, "Type": 4, "Size": 1, "LanePosition": 2, "JudgeTime": 27.700735092163086}, {"CastIndex": 0, "Type": 4, "Size": 1, "LanePosition": 2, "JudgeTime": 27.810224533081055}, {"CastIndex": 0, "Type": 4, "Size": 1, "LanePosition": 2, "JudgeTime": 27.919713973999023}, {"CastIndex": 0, "Type": 3, "Size": 1, "LanePosition": 2, "JudgeTime": 28.029203414916992}, {"CastIndex": 0, "Type": 4, "Size": 1, "LanePosition": 2, "JudgeTime": 28.13869285583496}, {"CastIndex": 0, "Type": 4, "Size": 1, "LanePosition": 2, "JudgeTime": 28.24818229675293}, {"CastIndex": 0, "Type": 4, "Size": 1, "LanePosition": 2, "JudgeTime": 28.357669830322266}, {"CastIndex": 0, "Type": 4, "Size": 1, "LanePosition": 2, "JudgeTime": 28.467159271240234}, {"CastIndex": 0, "Type": 4, "Size": 1, "LanePosition": 2, "JudgeTime": 28.576648712158203}, {"CastIndex": 0, "Type": 4, "Size": 1, "LanePosition": 2, "JudgeTime": 28.686138153076172}, {"CastIndex": 0, "Type": 4, "Size": 1, "LanePosition": 2, "JudgeTime": 28.79562759399414}, {"CastIndex": 0, "Type": 4, "Size": 1, "LanePosition": 2, "JudgeTime": 28.905115127563477}, {"CastIndex": 0, "Type": 4, "Size": 1, "LanePosition": 2, "JudgeTime": 29.014604568481445}, {"CastIndex": 0, "Type": 4, "Size": 1, "LanePosition": 2, "JudgeTime": 29.124094009399414}, {"CastIndex": 0, "Type": 5, "Size": 1.0, "LanePosition": 2.0, "JudgeTime": 29.1788387298584}, {"CastIndex": 0, "Type": 4, "Size": 3, "LanePosition": 1, "JudgeTime": 29.233583450317383}, {"CastIndex": 0, "Type": 4, "Size": 3, "LanePosition": 1, "JudgeTime": 29.34307289123535}, {"CastIndex": 0, "Type": 5, "Size": 1.5, "LanePosition": 1.75, "JudgeTime": 29.370445251464844}, {"CastIndex": 0, "Type": 5, "Size": 2.0, "LanePosition": 1.5, "JudgeTime": 29.452560424804688}, {"CastIndex": 0, "Type": 5, "Size": 2.5, "LanePosition": 1.25, "JudgeTime": 29.534677505493164}, {"CastIndex": 0, "Type": 4, "Size": 3, "LanePosition": 1, "JudgeTime": 29.562049865722656}, {"CastIndex": 0, "Type": 5, "Size": 3.0, "LanePosition": 1.0, "JudgeTime": 29.58942222595215}, {"CastIndex": 0, "Type": 5, "Size": 3.5, "LanePosition": 0.75, "JudgeTime": 29.644166946411133}, {"CastIndex": 0, "Type": 4, "Size": 5, "LanePosition": 0, "JudgeTime": 29.671539306640625}, {"CastIndex": 0, "Type": 5, "Size": 4.0, "LanePosition": 0.5, "JudgeTime": 29.698911666870117}, {"CastIndex": 1, "Type": 2, "Size": 5, "LanePosition": 0, "JudgeTime": 29.781028747558594}, {"CastIndex": 1, "Type": 1, "Size": 2, "LanePosition": 1, "JudgeTime": 30.109495162963867}, {"CastIndex": 1, "Type": 1, "Size": 2, "LanePosition": 0, "JudgeTime": 30.437963485717773}, {"CastIndex": 1, "Type": 1, "Size": 2, "LanePosition": 2, "JudgeTime": 30.656940460205078}, {"CastIndex": 1, "Type": 4, "Size": 2, "LanePosition": 2, "JudgeTime": 30.766429901123047}, {"CastIndex": 1, "Type": 4, "Size": 2, "LanePosition": 2, "JudgeTime": 30.875919342041016}, {"CastIndex": 1, "Type": 2, "Size": 2, "LanePosition": 2, "JudgeTime": 30.985408782958984}, {"CastIndex": 1, "Type": 1, "Size": 2, "LanePosition": 0, "JudgeTime": 30.985408782958984}, {"CastIndex": 1, "Type": 4, "Size": 2, "LanePosition": 0, "JudgeTime": 31.094898223876953}, {"CastIndex": 1, "Type": 4, "Size": 2, "LanePosition": 0, "JudgeTime": 31.20438575744629}, {"CastIndex": 1, "Type": 1, "Size": 2, "LanePosition": 2, "JudgeTime": 31.313875198364258}, {"CastIndex": 1, "Type": 2, "Size": 2, "LanePosition": 0, "JudgeTime": 31.313875198364258}, {"CastIndex": 1, "Type": 4, "Size": 2, "LanePosition": 2, "JudgeTime": 31.423364639282227}, {"CastIndex": 1, "Type": 4, "Size": 2, "LanePosition": 2, "JudgeTime": 31.532854080200195}, {"CastIndex": 1, "Type": 4, "Size": 2, "LanePosition": 2, "JudgeTime": 31.642343521118164}, {"CastIndex": 1, "Type": 4, "Size": 2, "LanePosition": 2, "JudgeTime": 31.751832962036133}, {"CastIndex": 1, "Type": 4, "Size": 2, "LanePosition": 2, "JudgeTime": 31.86132049560547}, {"CastIndex": 1, "Type": 4, "Size": 2, "LanePosition": 2, "JudgeTime": 31.970809936523438}, {"CastIndex": 1, "Type": 4, "Size": 2, "LanePosition": 2, "JudgeTime": 32.080299377441406}, {"CastIndex": 1, "Type": 2, "Size": 2, "LanePosition": 2, "JudgeTime": 32.189788818359375}, {"CastIndex": 1, "Type": 1, "Size": 2, "LanePosition": 0, "JudgeTime": 32.40876770019531}, {"CastIndex": 2, "Type": 1, "Size": 2, "LanePosition": 2, "JudgeTime": 32.40876770019531}, {"CastIndex": 2, "Type": 4, "Size": 3, "LanePosition": 2, "JudgeTime": 32.51825714111328}, {"CastIndex": 2, "Type": 4, "Size": 3, "LanePosition": 2, "JudgeTime": 32.627742767333984}, {"CastIndex": 2, "Type": 2, "Size": 2, "LanePosition": 3, "JudgeTime": 32.73723220825195}, {"CastIndex": 1, "Type": 1, "Size": 2, "LanePosition": 1, "JudgeTime": 32.73723220825195}, {"CastIndex": 1, "Type": 4, "Size": 3, "LanePosition": 0, "JudgeTime": 32.84672164916992}, {"CastIndex": 1, "Type": 4, "Size": 3, "LanePosition": 0, "JudgeTime": 32.95621109008789}, {"CastIndex": 1, "Type": 2, "Size": 2, "LanePosition": 0, "JudgeTime": 33.06570053100586}, {"CastIndex": 2, "Type": 1, "Size": 2, "LanePosition": 2, "JudgeTime": 33.06570053100586}, {"CastIndex": 1, "Type": 1, "Size": 2, "LanePosition": 2, "JudgeTime": 33.6131477355957}, {"CastIndex": 1, "Type": 1, "Size": 2, "LanePosition": 3, "JudgeTime": 33.941612243652344}, {"CastIndex": 1, "Type": 1, "Size": 2, "LanePosition": 0, "JudgeTime": 34.16059112548828}, {"CastIndex": 1, "Type": 4, "Size": 2, "LanePosition": 0, "JudgeTime": 34.27008056640625}, {"CastIndex": 1, "Type": 4, "Size": 2, "LanePosition": 0, "JudgeTime": 34.37957000732422}, {"CastIndex": 1, "Type": 1, "Size": 2, "LanePosition": 3, "JudgeTime": 34.48905944824219}, {"CastIndex": 1, "Type": 2, "Size": 2, "LanePosition": 0, "JudgeTime": 34.48905944824219}, {"CastIndex": 1, "Type": 4, "Size": 2, "LanePosition": 3, "JudgeTime": 34.598548889160156}, {"CastIndex": 1, "Type": 4, "Size": 2, "LanePosition": 3, "JudgeTime": 34.708038330078125}, {"CastIndex": 1, "Type": 2, "Size": 2, "LanePosition": 3, "JudgeTime": 34.817527770996094}, {"CastIndex": 1, "Type": 1, "Size": 2, "LanePosition": 1, "JudgeTime": 34.817527770996094}, {"CastIndex": 1, "Type": 4, "Size": 2, "LanePosition": 1, "JudgeTime": 34.9270133972168}, {"CastIndex": 1, "Type": 4, "Size": 2, "LanePosition": 1, "JudgeTime": 35.036502838134766}, {"CastIndex": 1, "Type": 4, "Size": 2, "LanePosition": 1, "JudgeTime": 35.145992279052734}, {"CastIndex": 1, "Type": 4, "Size": 2, "LanePosition": 1, "JudgeTime": 35.2554817199707}, {"CastIndex": 1, "Type": 4, "Size": 2, "LanePosition": 1, "JudgeTime": 35.36497116088867}, {"CastIndex": 1, "Type": 2, "Size": 2, "LanePosition": 1, "JudgeTime": 35.47446060180664}, {"CastIndex": 1, "Type": 1, "Size": 2, "LanePosition": 3, "JudgeTime": 35.69343566894531}, {"CastIndex": 1, "Type": 1, "Size": 2, "LanePosition": 2, "JudgeTime": 35.91241455078125}, {"CastIndex": 2, "Type": 1, "Size": 1, "LanePosition": 4, "JudgeTime": 35.91241455078125}, {"CastIndex": 2, "Type": 1, "Size": 1, "LanePosition": 3, "JudgeTime": 36.240882873535156}, {"CastIndex": 1, "Type": 1, "Size": 2, "LanePosition": 1, "JudgeTime": 36.240882873535156}, {"CastIndex": 2, "Type": 1, "Size": 1, "LanePosition": 2, "JudgeTime": 36.56935119628906}, {"CastIndex": 1, "Type": 1, "Size": 2, "LanePosition": 0, "JudgeTime": 36.56935119628906}, {"CastIndex": 1, "Type": 4, "Size": 2, "LanePosition": 0, "JudgeTime": 36.678836822509766}, {"CastIndex": 1, "Type": 4, "Size": 2, "LanePosition": 0, "JudgeTime": 36.788326263427734}, {"CastIndex": 1, "Type": 4, "Size": 2, "LanePosition": 0, "JudgeTime": 36.8978157043457}, {"CastIndex": 1, "Type": 2, "Size": 2, "LanePosition": 0, "JudgeTime": 37.00730514526367}, {"CastIndex": 1, "Type": 1, "Size": 2, "LanePosition": 0, "JudgeTime": 37.44525909423828}, {"CastIndex": 1, "Type": 1, "Size": 2, "LanePosition": 0, "JudgeTime": 37.66423797607422}, {"CastIndex": 2, "Type": 1, "Size": 1, "LanePosition": 2, "JudgeTime": 37.66423797607422}, {"CastIndex": 1, "Type": 4, "Size": 2, "LanePosition": 0, "JudgeTime": 37.77372741699219}, {"CastIndex": 1, "Type": 2, "Size": 2, "LanePosition": 0, "JudgeTime": 37.883216857910156}, {"CastIndex": 1, "Type": 1, "Size": 2, "LanePosition": 1, "JudgeTime": 37.992706298828125}, {"CastIndex": 2, "Type": 1, "Size": 1, "LanePosition": 3, "JudgeTime": 37.992706298828125}, {"CastIndex": 1, "Type": 4, "Size": 2, "LanePosition": 1, "JudgeTime": 38.102195739746094}, {"CastIndex": 1, "Type": 2, "Size": 2, "LanePosition": 1, "JudgeTime": 38.21168518066406}, {"CastIndex": 2, "Type": 1, "Size": 1, "LanePosition": 4, "JudgeTime": 38.32117462158203}, {"CastIndex": 1, "Type": 1, "Size": 2, "LanePosition": 2, "JudgeTime": 38.32117462158203}, {"CastIndex": 1, "Type": 4, "Size": 2, "LanePosition": 2, "JudgeTime": 38.430660247802734}, {"CastIndex": 1, "Type": 4, "Size": 2, "LanePosition": 2, "JudgeTime": 38.5401496887207}, {"CastIndex": 1, "Type": 4, "Size": 2, "LanePosition": 2, "JudgeTime": 38.64963912963867}, {"CastIndex": 1, "Type": 2, "Size": 2, "LanePosition": 2, "JudgeTime": 38.75912857055664}, {"CastIndex": 2, "Type": 1, "Size": 2, "LanePosition": 0, "JudgeTime": 39.41606140136719}, {"CastIndex": 2, "Type": 4, "Size": 2, "LanePosition": 0, "JudgeTime": 39.525550842285156}, {"CastIndex": 2, "Type": 2, "Size": 2, "LanePosition": 0, "JudgeTime": 39.635040283203125}, {"CastIndex": 2, "Type": 1, "Size": 2, "LanePosition": 3, "JudgeTime": 39.744529724121094}, {"CastIndex": 2, "Type": 4, "Size": 2, "LanePosition": 3, "JudgeTime": 39.85401916503906}, {"CastIndex": 2, "Type": 4, "Size": 2, "LanePosition": 3, "JudgeTime": 39.96350860595703}, {"CastIndex": 2, "Type": 2, "Size": 2, "LanePosition": 3, "JudgeTime": 40.072998046875}, {"CastIndex": 2, "Type": 1, "Size": 2, "LanePosition": 1, "JudgeTime": 40.072998046875}, {"CastIndex": 2, "Type": 4, "Size": 2, "LanePosition": 1, "JudgeTime": 40.1824836730957}, {"CastIndex": 2, "Type": 4, "Size": 2, "LanePosition": 1, "JudgeTime": 40.29197311401367}, {"CastIndex": 2, "Type": 4, "Size": 2, "LanePosition": 1, "JudgeTime": 40.40146255493164}, {"CastIndex": 2, "Type": 4, "Size": 2, "LanePosition": 1, "JudgeTime": 40.51095199584961}, {"CastIndex": 2, "Type": 4, "Size": 2, "LanePosition": 1, "JudgeTime": 40.62044143676758}, {"CastIndex": 2, "Type": 2, "Size": 2, "LanePosition": 1, "JudgeTime": 40.72993087768555}, {"CastIndex": 2, "Type": 1, "Size": 2, "LanePosition": 2, "JudgeTime": 40.94890594482422}, {"CastIndex": 1, "Type": 1, "Size": 1, "LanePosition": 1, "JudgeTime": 41.167884826660156}, {"CastIndex": 2, "Type": 1, "Size": 2, "LanePosition": 3, "JudgeTime": 41.167884826660156}, {"CastIndex": 1, "Type": 1, "Size": 2, "LanePosition": 0, "JudgeTime": 41.49635314941406}, {"CastIndex": 2, "Type": 1, "Size": 1, "LanePosition": 4, "JudgeTime": 41.49635314941406}, {"CastIndex": 4, "Type": 1, "Size": 2, "LanePosition": 3, "JudgeTime": 42.26277542114258}, {"CastIndex": 0, "Type": 1, "Size": 1, "LanePosition": 0, "JudgeTime": 42.26277542114258}, {"CastIndex": 4, "Type": 4, "Size": 3, "LanePosition": 2, "JudgeTime": 42.37226486206055}, {"CastIndex": 0, "Type": 4, "Size": 1, "LanePosition": 0, "JudgeTime": 42.37226486206055}, {"CastIndex": 0, "Type": 4, "Size": 1, "LanePosition": 0, "JudgeTime": 42.481754302978516}, {"CastIndex": 3, "Type": 3, "Size": 2, "LanePosition": 1, "JudgeTime": 42.481754302978516}, {"CastIndex": 0, "Type": 4, "Size": 1, "LanePosition": 0, "JudgeTime": 42.59123992919922}, {"CastIndex": 3, "Type": 4, "Size": 2, "LanePosition": 2, "JudgeTime": 42.59123992919922}, {"CastIndex": 2, "Type": 3, "Size": 2, "LanePosition": 3, "JudgeTime": 42.70072937011719}, {"CastIndex": 0, "Type": 4, "Size": 1, "LanePosition": 0, "JudgeTime": 42.70072937011719}, {"CastIndex": 2, "Type": 4, "Size": 2, "LanePosition": 2, "JudgeTime": 42.810218811035156}, {"CastIndex": 0, "Type": 4, "Size": 1, "LanePosition": 0, "JudgeTime": 42.810218811035156}, {"CastIndex": 1, "Type": 3, "Size": 2, "LanePosition": 1, "JudgeTime": 42.919708251953125}, {"CastIndex": 0, "Type": 4, "Size": 1, "LanePosition": 0, "JudgeTime": 42.919708251953125}, {"CastIndex": 1, "Type": 4, "Size": 2, "LanePosition": 2, "JudgeTime": 43.029197692871094}, {"CastIndex": 0, "Type": 4, "Size": 1, "LanePosition": 0, "JudgeTime": 43.029197692871094}, {"CastIndex": 0, "Type": 3, "Size": 2, "LanePosition": 3, "JudgeTime": 43.13868713378906}, {"CastIndex": 0, "Type": 4, "Size": 1, "LanePosition": 0, "JudgeTime": 43.13868713378906}, {"CastIndex": 0, "Type": 4, "Size": 1, "LanePosition": 0, "JudgeTime": 43.24817657470703}, {"CastIndex": 0, "Type": 4, "Size": 2, "LanePosition": 2, "JudgeTime": 43.24817657470703}, {"CastIndex": 4, "Type": 3, "Size": 2, "LanePosition": 1, "JudgeTime": 43.357666015625}, {"CastIndex": 0, "Type": 4, "Size": 1, "LanePosition": 0, "JudgeTime": 43.357666015625}, {"CastIndex": 0, "Type": 4, "Size": 1, "LanePosition": 0, "JudgeTime": 43.46715545654297}, {"CastIndex": 4, "Type": 4, "Size": 2, "LanePosition": 2, "JudgeTime": 43.46715545654297}, {"CastIndex": 3, "Type": 2, "Size": 2, "LanePosition": 3, "JudgeTime": 43.57664489746094}, {"CastIndex": 0, "Type": 2, "Size": 1, "LanePosition": 0, "JudgeTime": 43.57664489746094}, {"CastIndex": 3, "Type": 1, "Size": 2, "LanePosition": 3, "JudgeTime": 43.79561996459961}, {"CastIndex": 4, "Type": 1, "Size": 2, "LanePosition": 2, "JudgeTime": 44.01459884643555}, {"CastIndex": 4, "Type": 1, "Size": 2, "LanePosition": 1, "JudgeTime": 44.233577728271484}, {"CastIndex": 4, "Type": 1, "Size": 2, "LanePosition": 0, "JudgeTime": 44.452552795410156}, {"CastIndex": 3, "Type": 1, "Size": 2, "LanePosition": 3, "JudgeTime": 44.671531677246094}, {"CastIndex": 4, "Type": 1, "Size": 2, "LanePosition": 2, "JudgeTime": 44.89051055908203}, {"CastIndex": 4, "Type": 1, "Size": 2, "LanePosition": 1, "JudgeTime": 45.10948944091797}, {"CastIndex": 4, "Type": 1, "Size": 2, "LanePosition": 0, "JudgeTime": 45.328468322753906}, {"CastIndex": 3, "Type": 1, "Size": 2, "LanePosition": 3, "JudgeTime": 45.54744338989258}, {"CastIndex": 4, "Type": 1, "Size": 2, "LanePosition": 2, "JudgeTime": 45.766422271728516}, {"CastIndex": 4, "Type": 1, "Size": 2, "LanePosition": 1, "JudgeTime": 45.98540115356445}, {"CastIndex": 4, "Type": 1, "Size": 2, "LanePosition": 0, "JudgeTime": 46.204376220703125}, {"CastIndex": 4, "Type": 1, "Size": 2, "LanePosition": 1, "JudgeTime": 46.42335510253906}, {"CastIndex": 3, "Type": 1, "Size": 2, "LanePosition": 3, "JudgeTime": 46.42335510253906}, {"CastIndex": 4, "Type": 4, "Size": 3, "LanePosition": 0, "JudgeTime": 46.53284454345703}, {"CastIndex": 4, "Type": 4, "Size": 3, "LanePosition": 0, "JudgeTime": 46.642333984375}, {"CastIndex": 4, "Type": 4, "Size": 3, "LanePosition": 0, "JudgeTime": 46.75182342529297}, {"CastIndex": 4, "Type": 2, "Size": 2, "LanePosition": 0, "JudgeTime": 46.86131286621094}, {"CastIndex": 3, "Type": 1, "Size": 2, "LanePosition": 0, "JudgeTime": 47.29926681518555}, {"CastIndex": 4, "Type": 1, "Size": 2, "LanePosition": 1, "JudgeTime": 47.518245697021484}, {"CastIndex": 4, "Type": 1, "Size": 2, "LanePosition": 2, "JudgeTime": 47.73722457885742}, {"CastIndex": 4, "Type": 1, "Size": 2, "LanePosition": 3, "JudgeTime": 47.956199645996094}, {"CastIndex": 4, "Type": 1, "Size": 2, "LanePosition": 3, "JudgeTime": 48.17517852783203}, {"CastIndex": 3, "Type": 1, "Size": 2, "LanePosition": 0, "JudgeTime": 48.17517852783203}, {"CastIndex": 4, "Type": 1, "Size": 2, "LanePosition": 2, "JudgeTime": 48.39415740966797}, {"CastIndex": 4, "Type": 1, "Size": 2, "LanePosition": 1, "JudgeTime": 48.50364685058594}, {"CastIndex": 4, "Type": 1, "Size": 2, "LanePosition": 0, "JudgeTime": 48.832115173339844}, {"CastIndex": 4, "Type": 4, "Size": 3, "LanePosition": 0, "JudgeTime": 48.94160079956055}, {"CastIndex": 4, "Type": 4, "Size": 3, "LanePosition": 0, "JudgeTime": 49.051090240478516}, {"CastIndex": 4, "Type": 4, "Size": 3, "LanePosition": 0, "JudgeTime": 49.160579681396484}, {"CastIndex": 4, "Type": 4, "Size": 3, "LanePosition": 0, "JudgeTime": 49.27006912231445}, {"CastIndex": 4, "Type": 4, "Size": 4, "LanePosition": 0, "JudgeTime": 49.37955856323242}, {"CastIndex": 4, "Type": 4, "Size": 4, "LanePosition": 0, "JudgeTime": 49.48904800415039}, {"CastIndex": 4, "Type": 4, "Size": 4, "LanePosition": 0, "JudgeTime": 49.598533630371094}, {"CastIndex": 4, "Type": 4, "Size": 4, "LanePosition": 0, "JudgeTime": 49.70802307128906}, {"CastIndex": 4, "Type": 4, "Size": 4, "LanePosition": 0, "JudgeTime": 49.81751251220703}, {"CastIndex": 4, "Type": 4, "Size": 5, "LanePosition": 0, "JudgeTime": 49.927001953125}, {"CastIndex": 4, "Type": 4, "Size": 5, "LanePosition": 0, "JudgeTime": 50.03649139404297}, {"CastIndex": 4, "Type": 4, "Size": 5, "LanePosition": 0, "JudgeTime": 50.14598083496094}, {"CastIndex": 4, "Type": 4, "Size": 5, "LanePosition": 0, "JudgeTime": 50.255470275878906}, {"CastIndex": 4, "Type": 2, "Size": 5, "LanePosition": 0, "JudgeTime": 50.364959716796875}, {"CastIndex": 3, "Type": 1, "Size": 2, "LanePosition": 0, "JudgeTime": 50.802913665771484}, {"CastIndex": 3, "Type": 1, "Size": 2, "LanePosition": 3, "JudgeTime": 50.802913665771484}, {"CastIndex": 3, "Type": 1, "Size": 2, "LanePosition": 2, "JudgeTime": 50.94889831542969}, {"CastIndex": 3, "Type": 1, "Size": 2, "LanePosition": 1, "JudgeTime": 51.09488296508789}, {"CastIndex": 3, "Type": 1, "Size": 2, "LanePosition": 2, "JudgeTime": 51.24087142944336}, {"CastIndex": 3, "Type": 1, "Size": 2, "LanePosition": 1, "JudgeTime": 51.38685607910156}, {"CastIndex": 3, "Type": 1, "Size": 2, "LanePosition": 0, "JudgeTime": 51.532840728759766}, {"CastIndex": 3, "Type": 4, "Size": 2, "LanePosition": 0, "JudgeTime": 51.5693359375}, {"CastIndex": 3, "Type": 4, "Size": 2, "LanePosition": 0, "JudgeTime": 51.67882537841797}, {"CastIndex": 3, "Type": 4, "Size": 2, "LanePosition": 0, "JudgeTime": 51.78831481933594}, {"CastIndex": 3, "Type": 4, "Size": 2, "LanePosition": 0, "JudgeTime": 51.897804260253906}, {"CastIndex": 3, "Type": 4, "Size": 2, "LanePosition": 0, "JudgeTime": 52.007293701171875}, {"CastIndex": 3, "Type": 2, "Size": 2, "LanePosition": 0, "JudgeTime": 52.116783142089844}, {"CastIndex": 3, "Type": 1, "Size": 2, "LanePosition": 3, "JudgeTime": 52.55473709106445}, {"CastIndex": 3, "Type": 1, "Size": 2, "LanePosition": 0, "JudgeTime": 52.55473709106445}, {"CastIndex": 3, "Type": 1, "Size": 2, "LanePosition": 2, "JudgeTime": 52.700721740722656}, {"CastIndex": 3, "Type": 1, "Size": 2, "LanePosition": 1, "JudgeTime": 52.84670639038086}, {"CastIndex": 3, "Type": 1, "Size": 2, "LanePosition": 2, "JudgeTime": 52.99269485473633}, {"CastIndex": 3, "Type": 1, "Size": 2, "LanePosition": 1, "JudgeTime": 53.13867950439453}, {"CastIndex": 3, "Type": 1, "Size": 2, "LanePosition": 0, "JudgeTime": 53.284664154052734}, {"CastIndex": 3, "Type": 4, "Size": 2, "LanePosition": 0, "JudgeTime": 53.32115936279297}, {"CastIndex": 3, "Type": 4, "Size": 2, "LanePosition": 0, "JudgeTime": 53.43064880371094}, {"CastIndex": 3, "Type": 4, "Size": 2, "LanePosition": 0, "JudgeTime": 53.540138244628906}, {"CastIndex": 3, "Type": 4, "Size": 2, "LanePosition": 0, "JudgeTime": 53.649627685546875}, {"CastIndex": 3, "Type": 4, "Size": 2, "LanePosition": 0, "JudgeTime": 53.759117126464844}, {"CastIndex": 3, "Type": 2, "Size": 2, "LanePosition": 0, "JudgeTime": 53.86860656738281}, {"CastIndex": 3, "Type": 1, "Size": 2, "LanePosition": 2, "JudgeTime": 53.86860656738281}, {"CastIndex": 3, "Type": 1, "Size": 2, "LanePosition": 3, "JudgeTime": 54.08758544921875}, {"CastIndex": 3, "Type": 1, "Size": 2, "LanePosition": 1, "JudgeTime": 54.08758544921875}, {"CastIndex": 3, "Type": 4, "Size": 2, "LanePosition": 1, "JudgeTime": 54.19707107543945}, {"CastIndex": 3, "Type": 4, "Size": 2, "LanePosition": 3, "JudgeTime": 54.19707107543945}, {"CastIndex": 3, "Type": 4, "Size": 2, "LanePosition": 3, "JudgeTime": 54.30656051635742}, {"CastIndex": 3, "Type": 4, "Size": 2, "LanePosition": 1, "JudgeTime": 54.30656051635742}, {"CastIndex": 3, "Type": 4, "Size": 2, "LanePosition": 3, "JudgeTime": 54.41604995727539}, {"CastIndex": 3, "Type": 4, "Size": 2, "LanePosition": 1, "JudgeTime": 54.41604995727539}, {"CastIndex": 3, "Type": 4, "Size": 2, "LanePosition": 1, "JudgeTime": 54.52553939819336}, {"CastIndex": 3, "Type": 4, "Size": 2, "LanePosition": 3, "JudgeTime": 54.52553939819336}, {"CastIndex": 3, "Type": 4, "Size": 2, "LanePosition": 1, "JudgeTime": 54.63502883911133}, {"CastIndex": 3, "Type": 4, "Size": 2, "LanePosition": 3, "JudgeTime": 54.63502883911133}, {"CastIndex": 3, "Type": 2, "Size": 2, "LanePosition": 3, "JudgeTime": 54.7445182800293}, {"CastIndex": 3, "Type": 2, "Size": 2, "LanePosition": 1, "JudgeTime": 54.7445182800293}, {"CastIndex": 3, "Type": 1, "Size": 1, "LanePosition": 2, "JudgeTime": 54.96349334716797}, {"CastIndex": 3, "Type": 1, "Size": 2, "LanePosition": 0, "JudgeTime": 54.96349334716797}, {"CastIndex": 3, "Type": 4, "Size": 2, "LanePosition": 0, "JudgeTime": 55.07298278808594}, {"CastIndex": 3, "Type": 4, "Size": 2, "LanePosition": 0, "JudgeTime": 55.182472229003906}, {"CastIndex": 3, "Type": 4, "Size": 2, "LanePosition": 0, "JudgeTime": 55.291961669921875}, {"CastIndex": 3, "Type": 1, "Size": 1, "LanePosition": 3, "JudgeTime": 55.401451110839844}, {"CastIndex": 3, "Type": 4, "Size": 2, "LanePosition": 0, "JudgeTime": 55.401451110839844}, {"CastIndex": 3, "Type": 4, "Size": 2, "LanePosition": 0, "JudgeTime": 55.51094055175781}, {"CastIndex": 3, "Type": 4, "Size": 2, "LanePosition": 0, "JudgeTime": 55.62042999267578}, {"CastIndex": 3, "Type": 1, "Size": 1, "LanePosition": 4, "JudgeTime": 55.62042999267578}, {"CastIndex": 3, "Type": 4, "Size": 2, "LanePosition": 0, "JudgeTime": 55.72991943359375}, {"CastIndex": 3, "Type": 4, "Size": 2, "LanePosition": 0, "JudgeTime": 55.83940887451172}, {"CastIndex": 3, "Type": 1, "Size": 1, "LanePosition": 3, "JudgeTime": 55.83940887451172}, {"CastIndex": 3, "Type": 4, "Size": 2, "LanePosition": 0, "JudgeTime": 55.94889450073242}, {"CastIndex": 3, "Type": 1, "Size": 1, "LanePosition": 2, "JudgeTime": 56.05838394165039}, {"CastIndex": 3, "Type": 3, "Size": 2, "LanePosition": 0, "JudgeTime": 56.05838394165039}, {"CastIndex": 3, "Type": 4, "Size": 2, "LanePosition": 2, "JudgeTime": 56.16787338256836}, {"CastIndex": 3, "Type": 4, "Size": 3, "LanePosition": 0, "JudgeTime": 56.16787338256836}, {"CastIndex": 3, "Type": 4, "Size": 3, "LanePosition": 0, "JudgeTime": 56.27736282348633}, {"CastIndex": 3, "Type": 4, "Size": 2, "LanePosition": 2, "JudgeTime": 56.27736282348633}, {"CastIndex": 3, "Type": 4, "Size": 3, "LanePosition": 0, "JudgeTime": 56.3868522644043}, {"CastIndex": 3, "Type": 4, "Size": 2, "LanePosition": 2, "JudgeTime": 56.3868522644043}, {"CastIndex": 3, "Type": 4, "Size": 3, "LanePosition": 0, "JudgeTime": 56.496341705322266}, {"CastIndex": 3, "Type": 4, "Size": 2, "LanePosition": 2, "JudgeTime": 56.496341705322266}, {"CastIndex": 3, "Type": 4, "Size": 2, "LanePosition": 2, "JudgeTime": 56.60582733154297}, {"CastIndex": 3, "Type": 4, "Size": 3, "LanePosition": 0, "JudgeTime": 56.60582733154297}, {"CastIndex": 3, "Type": 4, "Size": 3, "LanePosition": 0, "JudgeTime": 56.71531677246094}, {"CastIndex": 3, "Type": 4, "Size": 1, "LanePosition": 3, "JudgeTime": 56.71531677246094}, {"CastIndex": 3, "Type": 4, "Size": 2, "LanePosition": 3, "JudgeTime": 56.824806213378906}, {"CastIndex": 3, "Type": 4, "Size": 3, "LanePosition": 0, "JudgeTime": 56.824806213378906}, {"CastIndex": 3, "Type": 4, "Size": 2, "LanePosition": 3, "JudgeTime": 56.934295654296875}, {"CastIndex": 3, "Type": 4, "Size": 3, "LanePosition": 0, "JudgeTime": 56.934295654296875}, {"CastIndex": 3, "Type": 4, "Size": 3, "LanePosition": 0, "JudgeTime": 57.043785095214844}, {"CastIndex": 3, "Type": 4, "Size": 2, "LanePosition": 3, "JudgeTime": 57.043785095214844}, {"CastIndex": 3, "Type": 4, "Size": 2, "LanePosition": 3, "JudgeTime": 57.15327453613281}, {"CastIndex": 3, "Type": 4, "Size": 3, "LanePosition": 0, "JudgeTime": 57.15327453613281}, {"CastIndex": 3, "Type": 4, "Size": 3, "LanePosition": 0, "JudgeTime": 57.26276397705078}, {"CastIndex": 3, "Type": 4, "Size": 2, "LanePosition": 3, "JudgeTime": 57.26276397705078}, {"CastIndex": 3, "Type": 2, "Size": 2, "LanePosition": 1, "JudgeTime": 57.37225341796875}, {"CastIndex": 3, "Type": 2, "Size": 1, "LanePosition": 4, "JudgeTime": 57.37225341796875}, {"CastIndex": 0, "Type": 1, "Size": 2, "LanePosition": 0, "JudgeTime": 57.81020736694336}, {"CastIndex": 0, "Type": 5, "Size": 1.75, "LanePosition": 0.5, "JudgeTime": 57.8923225402832}, {"CastIndex": 0, "Type": 4, "Size": 3, "LanePosition": 0, "JudgeTime": 57.91969680786133}, {"CastIndex": 4, "Type": 1, "Size": 2, "LanePosition": 3, "JudgeTime": 58.0291862487793}, {"CastIndex": 0, "Type": 5, "Size": 1.5, "LanePosition": 1.0, "JudgeTime": 58.0291862487793}, {"CastIndex": 4, "Type": 5, "Size": 1.75, "LanePosition": 2.5, "JudgeTime": 58.11130142211914}, {"CastIndex": 4, "Type": 4, "Size": 3, "LanePosition": 2, "JudgeTime": 58.138675689697266}, {"CastIndex": 0, "Type": 4, "Size": 2, "LanePosition": 1, "JudgeTime": 58.138675689697266}, {"CastIndex": 4, "Type": 5, "Size": 1.5, "LanePosition": 2.25, "JudgeTime": 58.22079086303711}, {"CastIndex": 4, "Type": 4, "Size": 2, "LanePosition": 2, "JudgeTime": 58.248165130615234}, {"CastIndex": 0, "Type": 4, "Size": 2, "LanePosition": 1, "JudgeTime": 58.248165130615234}, {"CastIndex": 2, "Type": 1, "Size": 2, "LanePosition": 0, "JudgeTime": 58.248165130615234}, {"CastIndex": 2, "Type": 5, "Size": 1.75, "LanePosition": 0.75, "JudgeTime": 58.33028030395508}, {"CastIndex": 2, "Type": 4, "Size": 3, "LanePosition": 0, "JudgeTime": 58.35765075683594}, {"CastIndex": 0, "Type": 4, "Size": 2, "LanePosition": 1, "JudgeTime": 58.35765075683594}, {"CastIndex": 4, "Type": 4, "Size": 2, "LanePosition": 2, "JudgeTime": 58.35765075683594}, {"CastIndex": 0, "Type": 5, "Size": 1.0, "LanePosition": 2.0, "JudgeTime": 58.38502502441406}, {"CastIndex": 2, "Type": 5, "Size": 1.5, "LanePosition": 1.25, "JudgeTime": 58.43976974487305}, {"CastIndex": 0, "Type": 4, "Size": 1, "LanePosition": 2, "JudgeTime": 58.467140197753906}, {"CastIndex": 4, "Type": 4, "Size": 2, "LanePosition": 2, "JudgeTime": 58.467140197753906}, {"CastIndex": 2, "Type": 4, "Size": 2, "LanePosition": 1, "JudgeTime": 58.467140197753906}, {"CastIndex": 3, "Type": 1, "Size": 2, "LanePosition": 3, "JudgeTime": 58.467140197753906}, {"CastIndex": 4, "Type": 5, "Size": 1.0, "LanePosition": 2.0, "JudgeTime": 58.49451446533203}, {"CastIndex": 4, "Type": 4, "Size": 1, "LanePosition": 2, "JudgeTime": 58.576629638671875}, {"CastIndex": 2, "Type": 4, "Size": 2, "LanePosition": 1, "JudgeTime": 58.576629638671875}, {"CastIndex": 0, "Type": 4, "Size": 1, "LanePosition": 2, "JudgeTime": 58.576629638671875}, {"CastIndex": 3, "Type": 5, "Size": 1.75, "LanePosition": 2.5, "JudgeTime": 58.576629638671875}, {"CastIndex": 4, "Type": 4, "Size": 1, "LanePosition": 2, "JudgeTime": 58.686119079589844}, {"CastIndex": 3, "Type": 5, "Size": 1.5, "LanePosition": 2.25, "JudgeTime": 58.686119079589844}, {"CastIndex": 0, "Type": 4, "Size": 1, "LanePosition": 2, "JudgeTime": 58.686119079589844}, {"CastIndex": 2, "Type": 4, "Size": 2, "LanePosition": 1, "JudgeTime": 58.686119079589844}, {"CastIndex": 1, "Type": 1, "Size": 2, "LanePosition": 0, "JudgeTime": 58.686119079589844}, {"CastIndex": 2, "Type": 5, "Size": 1.0, "LanePosition": 2.0, "JudgeTime": 58.71349334716797}, {"CastIndex": 1, "Type": 5, "Size": 1.75, "LanePosition": 0.5, "JudgeTime": 58.76823806762695}, {"CastIndex": 3, "Type": 4, "Size": 2, "LanePosition": 2, "JudgeTime": 58.79560852050781}, {"CastIndex": 1, "Type": 4, "Size": 3, "LanePosition": 0, "JudgeTime": 58.79560852050781}, {"CastIndex": 0, "Type": 4, "Size": 1, "LanePosition": 2, "JudgeTime": 58.79560852050781}, {"CastIndex": 4, "Type": 4, "Size": 1, "LanePosition": 2, "JudgeTime": 58.79560852050781}, {"CastIndex": 2, "Type": 4, "Size": 1, "LanePosition": 2, "JudgeTime": 58.79560852050781}, {"CastIndex": 4, "Type": 4, "Size": 1, "LanePosition": 2, "JudgeTime": 58.90509796142578}, {"CastIndex": 2, "Type": 4, "Size": 1, "LanePosition": 2, "JudgeTime": 58.90509796142578}, {"CastIndex": 0, "Type": 4, "Size": 1, "LanePosition": 2, "JudgeTime": 58.90509796142578}, {"CastIndex": 3, "Type": 4, "Size": 2, "LanePosition": 2, "JudgeTime": 58.90509796142578}, {"CastIndex": 1, "Type": 5, "Size": 1.5, "LanePosition": 1.0, "JudgeTime": 58.90509796142578}, {"CastIndex": 1, "Type": 4, "Size": 2, "LanePosition": 1, "JudgeTime": 59.01458740234375}, {"CastIndex": 2, "Type": 4, "Size": 1, "LanePosition": 2, "JudgeTime": 59.01458740234375}, {"CastIndex": 0, "Type": 4, "Size": 1, "LanePosition": 2, "JudgeTime": 59.01458740234375}, {"CastIndex": 3, "Type": 4, "Size": 2, "LanePosition": 2, "JudgeTime": 59.01458740234375}, {"CastIndex": 0, "Type": 1, "Size": 1, "LanePosition": 4, "JudgeTime": 59.01458740234375}, {"CastIndex": 4, "Type": 4, "Size": 1, "LanePosition": 2, "JudgeTime": 59.01458740234375}, {"CastIndex": 0, "Type": 5, "Size": 1.0, "LanePosition": 3.5, "JudgeTime": 59.096702575683594}, {"CastIndex": 3, "Type": 5, "Size": 1.0, "LanePosition": 2.0, "JudgeTime": 59.096702575683594}, {"CastIndex": 0, "Type": 4, "Size": 1, "LanePosition": 2, "JudgeTime": 59.12407684326172}, {"CastIndex": 1, "Type": 4, "Size": 2, "LanePosition": 1, "JudgeTime": 59.12407684326172}, {"CastIndex": 0, "Type": 4, "Size": 2, "LanePosition": 3, "JudgeTime": 59.12407684326172}, {"CastIndex": 3, "Type": 4, "Size": 1, "LanePosition": 2, "JudgeTime": 59.12407684326172}, {"CastIndex": 4, "Type": 4, "Size": 1, "LanePosition": 2, "JudgeTime": 59.12407684326172}, {"CastIndex": 2, "Type": 4, "Size": 1, "LanePosition": 2, "JudgeTime": 59.12407684326172}, {"CastIndex": 0, "Type": 5, "Size": 1.0, "LanePosition": 3.0, "JudgeTime": 59.20619201660156}, {"CastIndex": 3, "Type": 4, "Size": 1, "LanePosition": 2, "JudgeTime": 59.23356628417969}, {"CastIndex": 0, "Type": 4, "Size": 2, "LanePosition": 2, "JudgeTime": 59.23356628417969}, {"CastIndex": 2, "Type": 4, "Size": 1, "LanePosition": 2, "JudgeTime": 59.23356628417969}, {"CastIndex": 0, "Type": 4, "Size": 1, "LanePosition": 2, "JudgeTime": 59.23356628417969}, {"CastIndex": 4, "Type": 4, "Size": 1, "LanePosition": 2, "JudgeTime": 59.23356628417969}, {"CastIndex": 1, "Type": 4, "Size": 2, "LanePosition": 1, "JudgeTime": 59.23356628417969}, {"CastIndex": 4, "Type": 4, "Size": 1, "LanePosition": 2, "JudgeTime": 59.343055725097656}, {"CastIndex": 2, "Type": 4, "Size": 1, "LanePosition": 2, "JudgeTime": 59.343055725097656}, {"CastIndex": 4, "Type": 1, "Size": 1, "LanePosition": 0, "JudgeTime": 59.343055725097656}, {"CastIndex": 0, "Type": 4, "Size": 1, "LanePosition": 2, "JudgeTime": 59.343055725097656}, {"CastIndex": 3, "Type": 4, "Size": 1, "LanePosition": 2, "JudgeTime": 59.343055725097656}, {"CastIndex": 1, "Type": 4, "Size": 2, "LanePosition": 1, "JudgeTime": 59.343055725097656}, {"CastIndex": 0, "Type": 4, "Size": 2, "LanePosition": 2, "JudgeTime": 59.343055725097656}, {"CastIndex": 1, "Type": 5, "Size": 1.0, "LanePosition": 2.0, "JudgeTime": 59.370426177978516}, {"CastIndex": 4, "Type": 5, "Size": 1.0, "LanePosition": 0.5, "JudgeTime": 59.370426177978516}, {"CastIndex": 4, "Type": 5, "Size": 1.0, "LanePosition": 1.0, "JudgeTime": 59.39780044555664}, {"CastIndex": 0, "Type": 5, "Size": 1.0, "LanePosition": 2.25, "JudgeTime": 59.4251708984375}, {"CastIndex": 4, "Type": 5, "Size": 1.0, "LanePosition": 1.5, "JudgeTime": 59.45254135131836}, {"CastIndex": 3, "Type": 4, "Size": 1, "LanePosition": 2, "JudgeTime": 59.45254135131836}, {"CastIndex": 0, "Type": 4, "Size": 2, "LanePosition": 2, "JudgeTime": 59.45254135131836}, {"CastIndex": 4, "Type": 4, "Size": 1, "LanePosition": 2, "JudgeTime": 59.45254135131836}, {"CastIndex": 1, "Type": 4, "Size": 1, "LanePosition": 2, "JudgeTime": 59.45254135131836}, {"CastIndex": 0, "Type": 4, "Size": 1, "LanePosition": 2, "JudgeTime": 59.45254135131836}, {"CastIndex": 2, "Type": 4, "Size": 1, "LanePosition": 2, "JudgeTime": 59.45254135131836}, {"CastIndex": 2, "Type": 2, "Size": 1, "LanePosition": 2, "JudgeTime": 59.56203079223633}, {"CastIndex": 2, "Type": 1, "Size": 1, "LanePosition": 3, "JudgeTime": 59.781009674072266}, {"CastIndex": 2, "Type": 1, "Size": 2, "LanePosition": 0, "JudgeTime": 59.9999885559082}, {"CastIndex": 2, "Type": 1, "Size": 1, "LanePosition": 2, "JudgeTime": 59.9999885559082}, {"CastIndex": 2, "Type": 1, "Size": 2, "LanePosition": 1, "JudgeTime": 60.218963623046875}, {"CastIndex": 2, "Type": 1, "Size": 1, "LanePosition": 4, "JudgeTime": 60.43794250488281}, {"CastIndex": 2, "Type": 1, "Size": 2, "LanePosition": 2, "JudgeTime": 60.43794250488281}, {"CastIndex": 2, "Type": 4, "Size": 2, "LanePosition": 3, "JudgeTime": 60.54743194580078}, {"CastIndex": 2, "Type": 2, "Size": 1, "LanePosition": 3, "JudgeTime": 60.65692138671875}, {"CastIndex": 2, "Type": 1, "Size": 2, "LanePosition": 1, "JudgeTime": 60.76641082763672}, {"CastIndex": 2, "Type": 1, "Size": 1, "LanePosition": 0, "JudgeTime": 60.76641082763672}, {"CastIndex": 2, "Type": 4, "Size": 2, "LanePosition": 0, "JudgeTime": 60.87590026855469}, {"CastIndex": 2, "Type": 2, "Size": 1, "LanePosition": 1, "JudgeTime": 60.985389709472656}, {"CastIndex": 2, "Type": 1, "Size": 2, "LanePosition": 3, "JudgeTime": 61.094879150390625}, {"CastIndex": 2, "Type": 1, "Size": 1, "LanePosition": 2, "JudgeTime": 61.094879150390625}, {"CastIndex": 2, "Type": 1, "Size": 1, "LanePosition": 4, "JudgeTime": 61.3138542175293}, {"CastIndex": 2, "Type": 1, "Size": 2, "LanePosition": 2, "JudgeTime": 61.3138542175293}, {"CastIndex": 2, "Type": 4, "Size": 3, "LanePosition": 1, "JudgeTime": 61.423343658447266}, {"CastIndex": 2, "Type": 4, "Size": 2, "LanePosition": 3, "JudgeTime": 61.423343658447266}, {"CastIndex": 2, "Type": 4, "Size": 3, "LanePosition": 0, "JudgeTime": 61.532833099365234}, {"CastIndex": 2, "Type": 4, "Size": 3, "LanePosition": 2, "JudgeTime": 61.532833099365234}, {"CastIndex": 2, "Type": 3, "Size": 2, "LanePosition": 2, "JudgeTime": 61.6423225402832}, {"CastIndex": 2, "Type": 3, "Size": 2, "LanePosition": 0, "JudgeTime": 61.6423225402832}, {"CastIndex": 2, "Type": 4, "Size": 3, "LanePosition": 0, "JudgeTime": 61.75181198120117}, {"CastIndex": 2, "Type": 4, "Size": 3, "LanePosition": 2, "JudgeTime": 61.75181198120117}, {"CastIndex": 2, "Type": 4, "Size": 3, "LanePosition": 0, "JudgeTime": 61.861297607421875}, {"CastIndex": 2, "Type": 4, "Size": 3, "LanePosition": 2, "JudgeTime": 61.861297607421875}, {"CastIndex": 2, "Type": 3, "Size": 2, "LanePosition": 1, "JudgeTime": 61.970787048339844}, {"CastIndex": 2, "Type": 3, "Size": 2, "LanePosition": 3, "JudgeTime": 61.970787048339844}, {"CastIndex": 2, "Type": 4, "Size": 3, "LanePosition": 2, "JudgeTime": 62.08027648925781}, {"CastIndex": 2, "Type": 4, "Size": 3, "LanePosition": 0, "JudgeTime": 62.08027648925781}, {"CastIndex": 2, "Type": 4, "Size": 3, "LanePosition": 0, "JudgeTime": 62.18976593017578}, {"CastIndex": 2, "Type": 4, "Size": 3, "LanePosition": 2, "JudgeTime": 62.18976593017578}, {"CastIndex": 2, "Type": 4, "Size": 3, "LanePosition": 0, "JudgeTime": 62.29925537109375}, {"CastIndex": 2, "Type": 4, "Size": 2, "LanePosition": 2, "JudgeTime": 62.29925537109375}, {"CastIndex": 2, "Type": 4, "Size": 2, "LanePosition": 2, "JudgeTime": 62.40874481201172}, {"CastIndex": 2, "Type": 4, "Size": 3, "LanePosition": 0, "JudgeTime": 62.40874481201172}, {"CastIndex": 2, "Type": 4, "Size": 2, "LanePosition": 2, "JudgeTime": 62.51823425292969}, {"CastIndex": 2, "Type": 4, "Size": 3, "LanePosition": 0, "JudgeTime": 62.51823425292969}, {"CastIndex": 2, "Type": 2, "Size": 2, "LanePosition": 0, "JudgeTime": 62.627723693847656}, {"CastIndex": 2, "Type": 2, "Size": 1, "LanePosition": 2, "JudgeTime": 62.627723693847656}, {"CastIndex": 2, "Type": 1, "Size": 1, "LanePosition": 1, "JudgeTime": 63.2846565246582}, {"CastIndex": 2, "Type": 1, "Size": 1, "LanePosition": 2, "JudgeTime": 63.50363540649414}, {"CastIndex": 2, "Type": 1, "Size": 2, "LanePosition": 3, "JudgeTime": 63.50363540649414}, {"CastIndex": 2, "Type": 1, "Size": 2, "LanePosition": 2, "JudgeTime": 63.72261047363281}, {"CastIndex": 2, "Type": 1, "Size": 2, "LanePosition": 1, "JudgeTime": 63.94158935546875}, {"CastIndex": 2, "Type": 1, "Size": 1, "LanePosition": 0, "JudgeTime": 63.94158935546875}, {"CastIndex": 2, "Type": 4, "Size": 2, "LanePosition": 0, "JudgeTime": 64.05107879638672}, {"CastIndex": 2, "Type": 2, "Size": 1, "LanePosition": 1, "JudgeTime": 64.16056823730469}, {"CastIndex": 2, "Type": 1, "Size": 2, "LanePosition": 2, "JudgeTime": 64.27005767822266}, {"CastIndex": 2, "Type": 1, "Size": 1, "LanePosition": 4, "JudgeTime": 64.27005767822266}, {"CastIndex": 2, "Type": 4, "Size": 2, "LanePosition": 3, "JudgeTime": 64.37954711914062}, {"CastIndex": 2, "Type": 4, "Size": 2, "LanePosition": 2, "JudgeTime": 64.4890365600586}, {"CastIndex": 2, "Type": 2, "Size": 1, "LanePosition": 2, "JudgeTime": 64.59852600097656}, {"CastIndex": 2, "Type": 1, "Size": 1, "LanePosition": 0, "JudgeTime": 64.8175048828125}, {"CastIndex": 2, "Type": 1, "Size": 2, "LanePosition": 1, "JudgeTime": 64.8175048828125}, {"CastIndex": 2, "Type": 4, "Size": 3, "LanePosition": 1, "JudgeTime": 64.92699432373047}, {"CastIndex": 2, "Type": 4, "Size": 2, "LanePosition": 0, "JudgeTime": 64.92699432373047}, {"CastIndex": 2, "Type": 4, "Size": 3, "LanePosition": 2, "JudgeTime": 65.03648376464844}, {"CastIndex": 2, "Type": 4, "Size": 3, "LanePosition": 0, "JudgeTime": 65.03648376464844}, {"CastIndex": 2, "Type": 3, "Size": 2, "LanePosition": 3, "JudgeTime": 65.1459732055664}, {"CastIndex": 2, "Type": 3, "Size": 2, "LanePosition": 1, "JudgeTime": 65.1459732055664}, {"CastIndex": 2, "Type": 4, "Size": 3, "LanePosition": 2, "JudgeTime": 65.25546264648438}, {"CastIndex": 2, "Type": 4, "Size": 3, "LanePosition": 0, "JudgeTime": 65.25546264648438}, {"CastIndex": 2, "Type": 4, "Size": 3, "LanePosition": 0, "JudgeTime": 65.36495208740234}, {"CastIndex": 2, "Type": 4, "Size": 3, "LanePosition": 2, "JudgeTime": 65.36495208740234}, {"CastIndex": 2, "Type": 4, "Size": 3, "LanePosition": 1, "JudgeTime": 65.47444152832031}, {"CastIndex": 2, "Type": 4, "Size": 3, "LanePosition": 0, "JudgeTime": 65.47444152832031}, {"CastIndex": 2, "Type": 4, "Size": 3, "LanePosition": 1, "JudgeTime": 65.58393096923828}, {"CastIndex": 2, "Type": 4, "Size": 3, "LanePosition": 0, "JudgeTime": 65.58393096923828}, {"CastIndex": 2, "Type": 4, "Size": 3, "LanePosition": 0, "JudgeTime": 65.69342041015625}, {"CastIndex": 2, "Type": 4, "Size": 3, "LanePosition": 0, "JudgeTime": 65.69342041015625}, {"CastIndex": 2, "Type": 4, "Size": 3, "LanePosition": 0, "JudgeTime": 65.80290985107422}, {"CastIndex": 2, "Type": 4, "Size": 3, "LanePosition": 0, "JudgeTime": 65.80290985107422}, {"CastIndex": 4, "Type": 2, "Size": 2, "LanePosition": 0, "JudgeTime": 65.91239166259766}, {"CastIndex": 4, "Type": 1, "Size": 2, "LanePosition": 1, "JudgeTime": 66.1313705444336}, {"CastIndex": 4, "Type": 1, "Size": 1, "LanePosition": 0, "JudgeTime": 66.1313705444336}, {"CastIndex": 4, "Type": 4, "Size": 3, "LanePosition": 1, "JudgeTime": 66.24085998535156}, {"CastIndex": 4, "Type": 4, "Size": 3, "LanePosition": 0, "JudgeTime": 66.24085998535156}, {"CastIndex": 2, "Type": 3, "Size": 1, "LanePosition": 4, "JudgeTime": 66.35034942626953}, {"CastIndex": 2, "Type": 3, "Size": 2, "LanePosition": 2, "JudgeTime": 66.35034942626953}, {"CastIndex": 2, "Type": 4, "Size": 2, "LanePosition": 3, "JudgeTime": 66.4598388671875}, {"CastIndex": 2, "Type": 4, "Size": 2, "LanePosition": 1, "JudgeTime": 66.4598388671875}, {"CastIndex": 2, "Type": 2, "Size": 2, "LanePosition": 0, "JudgeTime": 66.56932830810547}, {"CastIndex": 2, "Type": 2, "Size": 1, "LanePosition": 3, "JudgeTime": 66.56932830810547}, {"CastIndex": 1, "Type": 1, "Size": 2, "LanePosition": 2, "JudgeTime": 67.22626495361328}, {"CastIndex": 1, "Type": 1, "Size": 2, "LanePosition": 3, "JudgeTime": 67.44524383544922}, {"CastIndex": 1, "Type": 1, "Size": 2, "LanePosition": 0, "JudgeTime": 67.44524383544922}, {"CastIndex": 1, "Type": 1, "Size": 2, "LanePosition": 1, "JudgeTime": 67.66421508789062}, {"CastIndex": 1, "Type": 1, "Size": 2, "LanePosition": 2, "JudgeTime": 67.88319396972656}, {"CastIndex": 1, "Type": 1, "Size": 2, "LanePosition": 0, "JudgeTime": 68.1021728515625}, {"CastIndex": 1, "Type": 1, "Size": 2, "LanePosition": 3, "JudgeTime": 68.1021728515625}, {"CastIndex": 1, "Type": 1, "Size": 1, "LanePosition": 1, "JudgeTime": 68.32115173339844}, {"CastIndex": 1, "Type": 1, "Size": 1, "LanePosition": 3, "JudgeTime": 68.32115173339844}, {"CastIndex": 1, "Type": 4, "Size": 2, "LanePosition": 0, "JudgeTime": 68.4306411743164}, {"CastIndex": 1, "Type": 4, "Size": 2, "LanePosition": 3, "JudgeTime": 68.4306411743164}, {"CastIndex": 1, "Type": 4, "Size": 2, "LanePosition": 3, "JudgeTime": 68.54013061523438}, {"CastIndex": 1, "Type": 4, "Size": 2, "LanePosition": 0, "JudgeTime": 68.54013061523438}, {"CastIndex": 1, "Type": 2, "Size": 2, "LanePosition": 0, "JudgeTime": 68.64962005615234}, {"CastIndex": 1, "Type": 2, "Size": 2, "LanePosition": 3, "JudgeTime": 68.64962005615234}, {"CastIndex": 1, "Type": 1, "Size": 2, "LanePosition": 1, "JudgeTime": 68.97808837890625}, {"CastIndex": 1, "Type": 1, "Size": 2, "LanePosition": 2, "JudgeTime": 69.19706726074219}, {"CastIndex": 1, "Type": 4, "Size": 3, "LanePosition": 2, "JudgeTime": 69.30655670166016}, {"CastIndex": 1, "Type": 2, "Size": 1, "LanePosition": 4, "JudgeTime": 69.4160385131836}, {"CastIndex": 1, "Type": 1, "Size": 2, "LanePosition": 1, "JudgeTime": 69.52552795410156}, {"CastIndex": 1, "Type": 4, "Size": 3, "LanePosition": 0, "JudgeTime": 69.63501739501953}, {"CastIndex": 1, "Type": 4, "Size": 2, "LanePosition": 0, "JudgeTime": 69.7445068359375}, {"CastIndex": 1, "Type": 2, "Size": 1, "LanePosition": 0, "JudgeTime": 69.85399627685547}, {"CastIndex": 1, "Type": 1, "Size": 2, "LanePosition": 2, "JudgeTime": 70.29195404052734}, {"CastIndex": 1, "Type": 1, "Size": 2, "LanePosition": 3, "JudgeTime": 70.40144348144531}, {"CastIndex": 1, "Type": 1, "Size": 2, "LanePosition": 1, "JudgeTime": 70.51093292236328}, {"CastIndex": 1, "Type": 1, "Size": 2, "LanePosition": 2, "JudgeTime": 70.72991180419922}, {"CastIndex": 1, "Type": 1, "Size": 2, "LanePosition": 0, "JudgeTime": 70.94889068603516}, {"CastIndex": 1, "Type": 1, "Size": 2, "LanePosition": 1, "JudgeTime": 71.16786193847656}, {"CastIndex": 1, "Type": 1, "Size": 2, "LanePosition": 0, "JudgeTime": 71.27735137939453}, {"CastIndex": 1, "Type": 1, "Size": 2, "LanePosition": 0, "JudgeTime": 71.82479858398438}, {"CastIndex": 1, "Type": 1, "Size": 2, "LanePosition": 3, "JudgeTime": 71.82479858398438}, {"CastIndex": 1, "Type": 4, "Size": 3, "LanePosition": 2, "JudgeTime": 71.93428802490234}, {"CastIndex": 1, "Type": 4, "Size": 3, "LanePosition": 0, "JudgeTime": 71.93428802490234}, {"CastIndex": 1, "Type": 5, "Size": 2.25, "LanePosition": 2.5, "JudgeTime": 71.98902893066406}, {"CastIndex": 1, "Type": 5, "Size": 2.25, "LanePosition": 0.25, "JudgeTime": 71.98902893066406}, {"CastIndex": 1, "Type": 4, "Size": 3, "LanePosition": 2, "JudgeTime": 72.04377746582031}, {"CastIndex": 1, "Type": 4, "Size": 3, "LanePosition": 0, "JudgeTime": 72.04377746582031}, {"CastIndex": 1, "Type": 5, "Size": 2.5, "LanePosition": 0.5, "JudgeTime": 72.07115173339844}, {"CastIndex": 1, "Type": 5, "Size": 2.5, "LanePosition": 2.0, "JudgeTime": 72.07115173339844}, {"CastIndex": 1, "Type": 5, "Size": 2.75, "LanePosition": 0.75, "JudgeTime": 72.12589263916016}, {"CastIndex": 1, "Type": 5, "Size": 2.75, "LanePosition": 1.5, "JudgeTime": 72.12589263916016}, {"CastIndex": 1, "Type": 2, "Size": 3, "LanePosition": 1, "JudgeTime": 72.15326690673828}, {"CastIndex": 1, "Type": 1, "Size": 1, "LanePosition": 1, "JudgeTime": 72.48173522949219}, {"CastIndex": 1, "Type": 1, "Size": 1, "LanePosition": 3, "JudgeTime": 72.48173522949219}, {"CastIndex": 1, "Type": 1, "Size": 1, "LanePosition": 2, "JudgeTime": 72.70071411132812}, {"CastIndex": 1, "Type": 5, "Size": 2.0, "LanePosition": 1.5, "JudgeTime": 72.72808074951172}, {"CastIndex": 1, "Type": 5, "Size": 2.5, "LanePosition": 1.25, "JudgeTime": 72.75545501708984}, {"CastIndex": 1, "Type": 5, "Size": 3.0, "LanePosition": 1.0, "JudgeTime": 72.78282928466797}, {"CastIndex": 1, "Type": 4, "Size": 5, "LanePosition": 0, "JudgeTime": 72.8102035522461}, {"CastIndex": 1, "Type": 5, "Size": 3.5, "LanePosition": 0.75, "JudgeTime": 72.83757019042969}, {"CastIndex": 1, "Type": 4, "Size": 5, "LanePosition": 0, "JudgeTime": 72.91968536376953}, {"CastIndex": 1, "Type": 5, "Size": 4.0, "LanePosition": 0.5, "JudgeTime": 72.94705963134766}, {"CastIndex": 1, "Type": 4, "Size": 5, "LanePosition": 0, "JudgeTime": 73.0291748046875}, {"CastIndex": 1, "Type": 5, "Size": 4.0, "LanePosition": 0.5, "JudgeTime": 73.11129760742188}, {"CastIndex": 1, "Type": 4, "Size": 5, "LanePosition": 0, "JudgeTime": 73.13866424560547}, {"CastIndex": 1, "Type": 5, "Size": 3.5, "LanePosition": 0.75, "JudgeTime": 73.22078704833984}, {"CastIndex": 1, "Type": 4, "Size": 5, "LanePosition": 0, "JudgeTime": 73.24815368652344}, {"CastIndex": 1, "Type": 5, "Size": 3.0, "LanePosition": 1.0, "JudgeTime": 73.27552795410156}, {"CastIndex": 1, "Type": 5, "Size": 2.5, "LanePosition": 1.25, "JudgeTime": 73.30290222167969}, {"CastIndex": 1, "Type": 5, "Size": 2.0, "LanePosition": 1.5, "JudgeTime": 73.33027648925781}, {"CastIndex": 0, "Type": 2, "Size": 1, "LanePosition": 2, "JudgeTime": 73.3576431274414}, {"CastIndex": 0, "Type": 1, "Size": 2, "LanePosition": 0, "JudgeTime": 74.01457977294922}, {"CastIndex": 0, "Type": 1, "Size": 2, "LanePosition": 3, "JudgeTime": 74.01457977294922}, {"CastIndex": 0, "Type": 1, "Size": 2, "LanePosition": 2, "JudgeTime": 74.16056060791016}, {"CastIndex": 0, "Type": 1, "Size": 2, "LanePosition": 1, "JudgeTime": 74.30654907226562}, {"CastIndex": 0, "Type": 1, "Size": 2, "LanePosition": 3, "JudgeTime": 74.4525375366211}, {"CastIndex": 0, "Type": 1, "Size": 2, "LanePosition": 0, "JudgeTime": 74.4525375366211}, {"CastIndex": 0, "Type": 1, "Size": 2, "LanePosition": 1, "JudgeTime": 74.7445068359375}, {"CastIndex": 0, "Type": 1, "Size": 2, "LanePosition": 3, "JudgeTime": 74.89048767089844}, {"CastIndex": 0, "Type": 1, "Size": 2, "LanePosition": 1, "JudgeTime": 75.0364761352539}, {"CastIndex": 0, "Type": 1, "Size": 2, "LanePosition": 2, "JudgeTime": 75.18246459960938}, {"CastIndex": 0, "Type": 1, "Size": 2, "LanePosition": 3, "JudgeTime": 75.32844543457031}, {"CastIndex": 0, "Type": 1, "Size": 2, "LanePosition": 0, "JudgeTime": 75.32844543457031}, {"CastIndex": 0, "Type": 4, "Size": 2, "LanePosition": 3, "JudgeTime": 75.43793487548828}, {"CastIndex": 0, "Type": 4, "Size": 2, "LanePosition": 0, "JudgeTime": 75.43793487548828}, {"CastIndex": 0, "Type": 4, "Size": 2, "LanePosition": 0, "JudgeTime": 75.54742431640625}, {"CastIndex": 0, "Type": 4, "Size": 2, "LanePosition": 3, "JudgeTime": 75.54742431640625}, {"CastIndex": 0, "Type": 4, "Size": 2, "LanePosition": 3, "JudgeTime": 75.65691375732422}, {"CastIndex": 0, "Type": 4, "Size": 2, "LanePosition": 0, "JudgeTime": 75.65691375732422}, {"CastIndex": 0, "Type": 2, "Size": 2, "LanePosition": 0, "JudgeTime": 75.76640319824219}, {"CastIndex": 0, "Type": 2, "Size": 2, "LanePosition": 3, "JudgeTime": 75.76640319824219}, {"CastIndex": 0, "Type": 1, "Size": 2, "LanePosition": 1, "JudgeTime": 75.91238403320312}, {"CastIndex": 0, "Type": 1, "Size": 2, "LanePosition": 2, "JudgeTime": 76.0583724975586}, {"CastIndex": 0, "Type": 1, "Size": 2, "LanePosition": 2, "JudgeTime": 76.20436096191406}, {"CastIndex": 0, "Type": 1, "Size": 1, "LanePosition": 0, "JudgeTime": 76.20436096191406}, {"CastIndex": 0, "Type": 4, "Size": 3, "LanePosition": 2, "JudgeTime": 76.31385040283203}, {"CastIndex": 0, "Type": 4, "Size": 3, "LanePosition": 0, "JudgeTime": 76.31385040283203}, {"CastIndex": 0, "Type": 4, "Size": 2, "LanePosition": 3, "JudgeTime": 76.42333221435547}, {"CastIndex": 0, "Type": 4, "Size": 3, "LanePosition": 1, "JudgeTime": 76.42333221435547}, {"CastIndex": 0, "Type": 3, "Size": 2, "LanePosition": 2, "JudgeTime": 76.49633026123047}, {"CastIndex": 0, "Type": 3, "Size": 1, "LanePosition": 4, "JudgeTime": 76.49633026123047}, {"CastIndex": 0, "Type": 4, "Size": 2, "LanePosition": 3, "JudgeTime": 76.53282165527344}, {"CastIndex": 0, "Type": 4, "Size": 3, "LanePosition": 1, "JudgeTime": 76.53282165527344}, {"CastIndex": 0, "Type": 4, "Size": 2, "LanePosition": 1, "JudgeTime": 76.6423110961914}, {"CastIndex": 0, "Type": 4, "Size": 2, "LanePosition": 3, "JudgeTime": 76.6423110961914}, {"CastIndex": 0, "Type": 4, "Size": 2, "LanePosition": 0, "JudgeTime": 76.75180053710938}, {"CastIndex": 0, "Type": 4, "Size": 3, "LanePosition": 2, "JudgeTime": 76.75180053710938}, {"CastIndex": 0, "Type": 2, "Size": 2, "LanePosition": 2, "JudgeTime": 76.86128997802734}, {"CastIndex": 0, "Type": 2, "Size": 1, "LanePosition": 0, "JudgeTime": 76.86128997802734}, {"CastIndex": 0, "Type": 1, "Size": 1, "LanePosition": 0, "JudgeTime": 77.08026885986328}, {"CastIndex": 0, "Type": 1, "Size": 2, "LanePosition": 2, "JudgeTime": 77.08026885986328}, {"CastIndex": 0, "Type": 4, "Size": 2, "LanePosition": 2, "JudgeTime": 77.18975830078125}, {"CastIndex": 0, "Type": 4, "Size": 1, "LanePosition": 0, "JudgeTime": 77.18975830078125}, {"CastIndex": 0, "Type": 2, "Size": 2, "LanePosition": 2, "JudgeTime": 77.29924774169922}, {"CastIndex": 0, "Type": 2, "Size": 1, "LanePosition": 0, "JudgeTime": 77.29924774169922}, {"CastIndex": 0, "Type": 1, "Size": 2, "LanePosition": 3, "JudgeTime": 77.7372055053711}, {"CastIndex": 0, "Type": 1, "Size": 2, "LanePosition": 1, "JudgeTime": 77.95618438720703}, {"CastIndex": 0, "Type": 1, "Size": 1, "LanePosition": 4, "JudgeTime": 77.95618438720703}, {"CastIndex": 0, "Type": 4, "Size": 2, "LanePosition": 3, "JudgeTime": 78.065673828125}, {"CastIndex": 0, "Type": 4, "Size": 3, "LanePosition": 0, "JudgeTime": 78.065673828125}, {"CastIndex": 0, "Type": 4, "Size": 3, "LanePosition": 2, "JudgeTime": 78.17515563964844}, {"CastIndex": 0, "Type": 4, "Size": 2, "LanePosition": 0, "JudgeTime": 78.17515563964844}, {"CastIndex": 0, "Type": 3, "Size": 1, "LanePosition": 0, "JudgeTime": 78.2846450805664}, {"CastIndex": 0, "Type": 3, "Size": 2, "LanePosition": 2, "JudgeTime": 78.2846450805664}, {"CastIndex": 0, "Type": 4, "Size": 2, "LanePosition": 0, "JudgeTime": 78.39413452148438}, {"CastIndex": 0, "Type": 4, "Size": 3, "LanePosition": 2, "JudgeTime": 78.39413452148438}, {"CastIndex": 0, "Type": 4, "Size": 2, "LanePosition": 1, "JudgeTime": 78.50362396240234}, {"CastIndex": 0, "Type": 4, "Size": 2, "LanePosition": 3, "JudgeTime": 78.50362396240234}, {"CastIndex": 0, "Type": 3, "Size": 1, "LanePosition": 4, "JudgeTime": 78.61311340332031}, {"CastIndex": 0, "Type": 3, "Size": 2, "LanePosition": 2, "JudgeTime": 78.61311340332031}, {"CastIndex": 0, "Type": 4, "Size": 2, "LanePosition": 3, "JudgeTime": 78.72260284423828}, {"CastIndex": 0, "Type": 4, "Size": 3, "LanePosition": 1, "JudgeTime": 78.72260284423828}, {"CastIndex": 0, "Type": 4, "Size": 2, "LanePosition": 3, "JudgeTime": 78.83209228515625}, {"CastIndex": 0, "Type": 4, "Size": 2, "LanePosition": 1, "JudgeTime": 78.83209228515625}, {"CastIndex": 0, "Type": 4, "Size": 2, "LanePosition": 3, "JudgeTime": 78.94158172607422}, {"CastIndex": 0, "Type": 4, "Size": 2, "LanePosition": 1, "JudgeTime": 78.94158172607422}, {"CastIndex": 0, "Type": 4, "Size": 2, "LanePosition": 0, "JudgeTime": 79.05107116699219}, {"CastIndex": 0, "Type": 4, "Size": 3, "LanePosition": 2, "JudgeTime": 79.05107116699219}, {"CastIndex": 0, "Type": 4, "Size": 2, "LanePosition": 0, "JudgeTime": 79.16056060791016}, {"CastIndex": 0, "Type": 4, "Size": 3, "LanePosition": 2, "JudgeTime": 79.16056060791016}, {"CastIndex": 0, "Type": 2, "Size": 1, "LanePosition": 0, "JudgeTime": 79.27005004882812}, {"CastIndex": 0, "Type": 2, "Size": 2, "LanePosition": 2, "JudgeTime": 79.27005004882812}, {"CastIndex": 0, "Type": 1, "Size": 1, "LanePosition": 2, "JudgeTime": 79.7080078125}, {"CastIndex": 0, "Type": 4, "Size": 2, "LanePosition": 2, "JudgeTime": 79.81749725341797}, {"CastIndex": 0, "Type": 2, "Size": 2, "LanePosition": 3, "JudgeTime": 79.9269790649414}, {"CastIndex": 0, "Type": 1, "Size": 1, "LanePosition": 2, "JudgeTime": 80.03646850585938}, {"CastIndex": 0, "Type": 4, "Size": 2, "LanePosition": 1, "JudgeTime": 80.14595794677734}, {"CastIndex": 0, "Type": 4, "Size": 3, "LanePosition": 0, "JudgeTime": 80.25544738769531}, {"CastIndex": 0, "Type": 1, "Size": 2, "LanePosition": 3, "JudgeTime": 80.36493682861328}, {"CastIndex": 0, "Type": 2, "Size": 2, "LanePosition": 0, "JudgeTime": 80.36493682861328}, {"CastIndex": 0, "Type": 4, "Size": 3, "LanePosition": 2, "JudgeTime": 80.47442626953125}, {"CastIndex": 0, "Type": 4, "Size": 3, "LanePosition": 2, "JudgeTime": 80.58391571044922}, {"CastIndex": 4, "Type": 1, "Size": 2, "LanePosition": 0, "JudgeTime": 80.58391571044922}, {"CastIndex": 0, "Type": 4, "Size": 3, "LanePosition": 2, "JudgeTime": 80.69340515136719}, {"CastIndex": 0, "Type": 4, "Size": 3, "LanePosition": 2, "JudgeTime": 80.80289459228516}, {"CastIndex": 4, "Type": 1, "Size": 2, "LanePosition": 0, "JudgeTime": 80.91238403320312}, {"CastIndex": 0, "Type": 4, "Size": 3, "LanePosition": 2, "JudgeTime": 80.91238403320312}, {"CastIndex": 0, "Type": 4, "Size": 3, "LanePosition": 2, "JudgeTime": 81.0218734741211}, {"CastIndex": 0, "Type": 4, "Size": 3, "LanePosition": 2, "JudgeTime": 81.13136291503906}, {"CastIndex": 4, "Type": 1, "Size": 2, "LanePosition": 0, "JudgeTime": 81.24085235595703}, {"CastIndex": 0, "Type": 4, "Size": 3, "LanePosition": 2, "JudgeTime": 81.24085235595703}, {"CastIndex": 0, "Type": 4, "Size": 3, "LanePosition": 2, "JudgeTime": 81.350341796875}, {"CastIndex": 0, "Type": 4, "Size": 3, "LanePosition": 2, "JudgeTime": 81.45983123779297}, {"CastIndex": 4, "Type": 1, "Size": 2, "LanePosition": 0, "JudgeTime": 81.45983123779297}, {"CastIndex": 0, "Type": 4, "Size": 3, "LanePosition": 2, "JudgeTime": 81.56932067871094}, {"CastIndex": 0, "Type": 4, "Size": 3, "LanePosition": 2, "JudgeTime": 81.67880249023438}, {"CastIndex": 0, "Type": 4, "Size": 3, "LanePosition": 2, "JudgeTime": 81.78829193115234}, {"CastIndex": 4, "Type": 1, "Size": 2, "LanePosition": 0, "JudgeTime": 81.78829193115234}, {"CastIndex": 0, "Type": 4, "Size": 3, "LanePosition": 2, "JudgeTime": 81.89778137207031}, {"CastIndex": 0, "Type": 4, "Size": 3, "LanePosition": 2, "JudgeTime": 82.00727081298828}, {"CastIndex": 4, "Type": 1, "Size": 2, "LanePosition": 0, "JudgeTime": 82.11676025390625}, {"CastIndex": 0, "Type": 4, "Size": 3, "LanePosition": 2, "JudgeTime": 82.11676025390625}, {"CastIndex": 0, "Type": 4, "Size": 3, "LanePosition": 2, "JudgeTime": 82.22624969482422}, {"CastIndex": 4, "Type": 1, "Size": 2, "LanePosition": 0, "JudgeTime": 82.33573913574219}, {"CastIndex": 2, "Type": 2, "Size": 3, "LanePosition": 2, "JudgeTime": 82.33573913574219}, {"CastIndex": 4, "Type": 4, "Size": 3, "LanePosition": 0, "JudgeTime": 82.44522857666016}, {"CastIndex": 4, "Type": 4, "Size": 3, "LanePosition": 0, "JudgeTime": 82.55471801757812}, {"CastIndex": 2, "Type": 1, "Size": 2, "LanePosition": 3, "JudgeTime": 82.6642074584961}, {"CastIndex": 4, "Type": 4, "Size": 3, "LanePosition": 0, "JudgeTime": 82.6642074584961}, {"CastIndex": 4, "Type": 4, "Size": 3, "LanePosition": 0, "JudgeTime": 82.77369689941406}, {"CastIndex": 4, "Type": 4, "Size": 3, "LanePosition": 0, "JudgeTime": 82.88318634033203}, {"CastIndex": 2, "Type": 1, "Size": 2, "LanePosition": 3, "JudgeTime": 82.99267578125}, {"CastIndex": 4, "Type": 4, "Size": 3, "LanePosition": 0, "JudgeTime": 82.99267578125}, {"CastIndex": 4, "Type": 4, "Size": 3, "LanePosition": 0, "JudgeTime": 83.10216522216797}, {"CastIndex": 2, "Type": 1, "Size": 2, "LanePosition": 3, "JudgeTime": 83.21165466308594}, {"CastIndex": 4, "Type": 4, "Size": 3, "LanePosition": 0, "JudgeTime": 83.21165466308594}, {"CastIndex": 4, "Type": 4, "Size": 3, "LanePosition": 0, "JudgeTime": 83.3211441040039}, {"CastIndex": 4, "Type": 4, "Size": 3, "LanePosition": 0, "JudgeTime": 83.43062591552734}, {"CastIndex": 4, "Type": 4, "Size": 3, "LanePosition": 0, "JudgeTime": 83.54011535644531}, {"CastIndex": 4, "Type": 4, "Size": 3, "LanePosition": 0, "JudgeTime": 83.64960479736328}, {"CastIndex": 4, "Type": 4, "Size": 3, "LanePosition": 0, "JudgeTime": 83.75909423828125}, {"CastIndex": 4, "Type": 4, "Size": 3, "LanePosition": 0, "JudgeTime": 83.86858367919922}, {"CastIndex": 4, "Type": 4, "Size": 3, "LanePosition": 0, "JudgeTime": 83.97807312011719}, {"CastIndex": 2, "Type": 1, "Size": 2, "LanePosition": 3, "JudgeTime": 84.08756256103516}, {"CastIndex": 3, "Type": 2, "Size": 3, "LanePosition": 0, "JudgeTime": 84.08756256103516}, {"CastIndex": 2, "Type": 4, "Size": 2, "LanePosition": 3, "JudgeTime": 84.19705200195312}, {"CastIndex": 2, "Type": 4, "Size": 2, "LanePosition": 3, "JudgeTime": 84.3065414428711}, {"CastIndex": 3, "Type": 1, "Size": 2, "LanePosition": 0, "JudgeTime": 84.41603088378906}, {"CastIndex": 2, "Type": 4, "Size": 2, "LanePosition": 3, "JudgeTime": 84.41603088378906}, {"CastIndex": 2, "Type": 4, "Size": 2, "LanePosition": 3, "JudgeTime": 84.52552032470703}, {"CastIndex": 2, "Type": 4, "Size": 2, "LanePosition": 3, "JudgeTime": 84.635009765625}, {"CastIndex": 2, "Type": 4, "Size": 2, "LanePosition": 3, "JudgeTime": 84.74449920654297}, {"CastIndex": 3, "Type": 1, "Size": 2, "LanePosition": 0, "JudgeTime": 84.74449920654297}, {"CastIndex": 2, "Type": 4, "Size": 2, "LanePosition": 3, "JudgeTime": 84.85398864746094}, {"CastIndex": 2, "Type": 4, "Size": 2, "LanePosition": 3, "JudgeTime": 84.9634780883789}, {"CastIndex": 3, "Type": 1, "Size": 2, "LanePosition": 0, "JudgeTime": 84.9634780883789}, {"CastIndex": 2, "Type": 4, "Size": 2, "LanePosition": 3, "JudgeTime": 85.07296752929688}, {"CastIndex": 2, "Type": 4, "Size": 2, "LanePosition": 3, "JudgeTime": 85.18244934082031}, {"CastIndex": 3, "Type": 1, "Size": 2, "LanePosition": 0, "JudgeTime": 85.29193878173828}, {"CastIndex": 2, "Type": 4, "Size": 2, "LanePosition": 3, "JudgeTime": 85.29193878173828}, {"CastIndex": 2, "Type": 4, "Size": 2, "LanePosition": 3, "JudgeTime": 85.40142822265625}, {"CastIndex": 2, "Type": 4, "Size": 2, "LanePosition": 3, "JudgeTime": 85.51091766357422}, {"CastIndex": 2, "Type": 4, "Size": 2, "LanePosition": 3, "JudgeTime": 85.62040710449219}, {"CastIndex": 3, "Type": 1, "Size": 2, "LanePosition": 0, "JudgeTime": 85.62040710449219}, {"CastIndex": 2, "Type": 4, "Size": 2, "LanePosition": 3, "JudgeTime": 85.72989654541016}, {"CastIndex": 3, "Type": 1, "Size": 2, "LanePosition": 0, "JudgeTime": 85.83938598632812}, {"CastIndex": 0, "Type": 2, "Size": 2, "LanePosition": 3, "JudgeTime": 85.83938598632812}, {"CastIndex": 3, "Type": 4, "Size": 3, "LanePosition": 0, "JudgeTime": 85.9488754272461}, {"CastIndex": 3, "Type": 4, "Size": 3, "LanePosition": 0, "JudgeTime": 86.05836486816406}, {"CastIndex": 0, "Type": 1, "Size": 2, "LanePosition": 3, "JudgeTime": 86.16785430908203}, {"CastIndex": 3, "Type": 4, "Size": 3, "LanePosition": 0, "JudgeTime": 86.16785430908203}, {"CastIndex": 3, "Type": 4, "Size": 3, "LanePosition": 0, "JudgeTime": 86.27734375}, {"CastIndex": 3, "Type": 4, "Size": 3, "LanePosition": 0, "JudgeTime": 86.38683319091797}, {"CastIndex": 3, "Type": 4, "Size": 3, "LanePosition": 0, "JudgeTime": 86.49632263183594}, {"CastIndex": 0, "Type": 1, "Size": 2, "LanePosition": 3, "JudgeTime": 86.49632263183594}, {"CastIndex": 3, "Type": 4, "Size": 3, "LanePosition": 0, "JudgeTime": 86.6058120727539}, {"CastIndex": 3, "Type": 4, "Size": 3, "LanePosition": 0, "JudgeTime": 86.71530151367188}, {"CastIndex": 0, "Type": 1, "Size": 2, "LanePosition": 3, "JudgeTime": 86.71530151367188}, {"CastIndex": 3, "Type": 4, "Size": 3, "LanePosition": 0, "JudgeTime": 86.82479095458984}, {"CastIndex": 3, "Type": 4, "Size": 3, "LanePosition": 0, "JudgeTime": 86.93427276611328}, {"CastIndex": 3, "Type": 4, "Size": 3, "LanePosition": 0, "JudgeTime": 87.04376220703125}, {"CastIndex": 0, "Type": 1, "Size": 2, "LanePosition": 3, "JudgeTime": 87.04376220703125}, {"CastIndex": 3, "Type": 4, "Size": 3, "LanePosition": 0, "JudgeTime": 87.15325164794922}, {"CastIndex": 3, "Type": 4, "Size": 3, "LanePosition": 0, "JudgeTime": 87.26274108886719}, {"CastIndex": 0, "Type": 1, "Size": 2, "LanePosition": 3, "JudgeTime": 87.37223052978516}, {"CastIndex": 1, "Type": 2, "Size": 3, "LanePosition": 0, "JudgeTime": 87.37223052978516}]